Workbook

Sheet 购销发票税收分类编码
A1: 序号 | B1: 一级分类 | C1: 二级分类 | D1: 商品和服务分类简称 | E1: 税收分类编码 | F1: 货物和劳务名称 | G1: 说明 | H1: 碳排放范围分类 | I1: 所属行业 | J1: 对应行业排放因子 | K1: 废弃物处置分类
A2: 1 | B2: 农、林、牧、渔业类产品 | C2: 农业产品 | D2: 谷物 | E2: 1010101010000000000 | F2: 稻谷 | G2: 包括早籼稻、晚籼稻、中籼稻、粳稻、糯稻、其他稻谷。 | H2: 范围3 | I2: =VLOOKUP(F2,[1]完整分类结果!$E:$G,3,0) -> 农、林、牧、渔及水利业 | J2: =VLOOKUP(I2,[2]行业排放因子!$A:$B,2,0) -> 90.746323 | K2: 农业固体废弃物（Agricultural Solid Waste）
A3: 2 | B3: 农、林、牧、渔业类产品 | C3: 农业产品 | D3: 谷物 | E3: 1010101020000000000 | F3: 小麦 | G3: 包括硬质小麦、软质小麦、其他小麦。 | H3: 范围3 | I3: =VLOOKUP(F3,[1]完整分类结果!$E:$G,3,0) -> 农、林、牧、渔及水利业 | J3: =VLOOKUP(I3,[2]行业排放因子!$A:$B,2,0) -> 90.746323 | K3: 农业固体废弃物（Agricultural Solid Waste）
A4: 3 | B4: 农、林、牧、渔业类产品 | C4: 农业产品 | D4: 谷物 | E4: 1010101030000000000 | F4: 玉米 | G4: 包括白玉米、黄玉米、糯玉米、甜玉米、其他玉米。 | H4: 范围3 | I4: =VLOOKUP(F4,[1]完整分类结果!$E:$G,3,0) -> 农、林、牧、渔及水利业 | J4: =VLOOKUP(I4,[2]行业排放因子!$A:$B,2,0) -> 90.746323 | K4: 农业固体废弃物（Agricultural Solid Waste）
A5: 4 | B5: 农、林、牧、渔业类产品 | C5: 农业产品 | D5: 谷物 | E5: 1010101040000000000 | F5: 谷子 | G5: 包括硬谷子、糯谷子、其他谷子。 | H5: 范围3 | I5: =VLOOKUP(F5,[1]完整分类结果!$E:$G,3,0) -> 农、林、牧、渔及水利业 | J5: =VLOOKUP(I5,[2]行业排放因子!$A:$B,2,0) -> 90.746323 | K5: 农业固体废弃物（Agricultural Solid Waste）
A6: 5 | B6: 农、林、牧、渔业类产品 | C6: 农业产品 | D6: 谷物 | E6: 1010101050000000000 | F6: 高粱 | G6: 包括红粒高粱、白粒高粱、糯高粱、其他高粱。 | H6: 范围3 | I6: =VLOOKUP(F6,[1]完整分类结果!$E:$G,3,0) -> 农、林、牧、渔及水利业 | J6: =VLOOKUP(I6,[2]行业排放因子!$A:$B,2,0) -> 90.746323 | K6: 农业固体废弃物（Agricultural Solid Waste）
A7: 6 | B7: 农、林、牧、渔业类产品 | C7: 农业产品 | D7: 谷物 | E7: 1010101060000000000 | F7: 大麦 | G7: 包括裸大麦、皮大麦。 | H7: 范围3 | I7: =VLOOKUP(F7,[1]完整分类结果!$E:$G,3,0) -> 农、林、牧、渔及水利业 | J7: =VLOOKUP(I7,[2]行业排放因子!$A:$B,2,0) -> 90.746323 | K7: 农业固体废弃物（Agricultural Solid Waste）
A8: 7 | B8: 农、林、牧、渔业类产品 | C8: 农业产品 | D8: 谷物 | E8: 1010101070000000000 | F8: 燕麦 | G8: 包括裸燕麦、皮燕麦。 | H8: 范围3 | I8: =VLOOKUP(F8,[1]完整分类结果!$E:$G,3,0) -> 农、林、牧、渔及水利业 | J8: =VLOOKUP(I8,[2]行业排放因子!$A:$B,2,0) -> 90.746323 | K8: 农业固体废弃物（Agricultural Solid Waste）
A9: 8 | B9: 农、林、牧、渔业类产品 | C9: 农业产品 | D9: 谷物 | E9: 1010101080000000000 | F9: 黑麦 | H9: 范围3 | I9: =VLOOKUP(F9,[1]完整分类结果!$E:$G,3,0) -> 农、林、牧、渔及水利业 | J9: =VLOOKUP(I9,[2]行业排放因子!$A:$B,2,0) -> 90.746323 | K9: 农业固体废弃物（Agricultural Solid Waste）
A10: 9 | B10: 农、林、牧、渔业类产品 | C10: 农业产品 | D10: 谷物 | E10: 1010101090000000000 | F10: 荞麦 | G10: 包括甜荞麦、苦荞麦。 | H10: 范围3 | I10: =VLOOKUP(F10,[1]完整分类结果!$E:$G,3,0) -> 农、林、牧、渔及水利业 | J10: =VLOOKUP(I10,[2]行业排放因子!$A:$B,2,0) -> 90.746323 | K10: 农业固体废弃物（Agricultural Solid Waste）
A11: 10 | B11: 农、林、牧、渔业类产品 | C11: 农业产品 | D11: 谷物 | E11: 1010101990000000000 | F11: 其他谷物 | G11: 包括糜子（硬糜子、糯糜子）、紫米、薏苡等。 | H11: 范围3 | I11: =VLOOKUP(F11,[1]完整分类结果!$E:$G,3,0) -> 农、林、牧、渔及水利业 | J11: =VLOOKUP(I11,[2]行业排放因子!$A:$B,2,0) -> 90.746323 | K11: 农业固体废弃物（Agricultural Solid Waste）
A12: 11 | B12: 农、林、牧、渔业类产品 | C12: 农业产品 | D12: 薯类 | E12: 1010102010000000000 | F12: 马铃薯 | G12: 又称土豆、山药蛋。 | H12: 范围3 | I12: =VLOOKUP(F12,[1]完整分类结果!$E:$G,3,0) -> 农、林、牧、渔及水利业 | J12: =VLOOKUP(I12,[2]行业排放因子!$A:$B,2,0) -> 90.746323 | K12: 农业固体废弃物（Agricultural Solid Waste）
A13: 12 | B13: 农、林、牧、渔业类产品 | C13: 农业产品 | D13: 薯类 | E13: 1010102020000000000 | F13: 木薯 | G13: 包括鲜木薯、木薯干、其他木薯。 | H13: 范围3 | I13: =VLOOKUP(F13,[1]完整分类结果!$E:$G,3,0) -> 农、林、牧、渔及水利业 | J13: =VLOOKUP(I13,[2]行业排放因子!$A:$B,2,0) -> 90.746323 | K13: 农业固体废弃物（Agricultural Solid Waste）
A14: 13 | B14: 农、林、牧、渔业类产品 | C14: 农业产品 | D14: 薯类 | E14: 1010102030000000000 | F14: 甘薯 | G14: 又称红薯、白薯、地瓜、番薯、包括甘薯干、其他鲜甘薯。 | H14: 范围3 | I14: =VLOOKUP(F14,[1]完整分类结果!$E:$G,3,0) -> 农、林、牧、渔及水利业 | J14: =VLOOKUP(I14,[2]行业排放因子!$A:$B,2,0) -> 90.746323 | K14: 农业固体废弃物（Agricultural Solid Waste）
A15: 14 | B15: 农、林、牧、渔业类产品 | C15: 农业产品 | D15: 薯类 | E15: 1010102990000000000 | F15: 其他薯类 | G15: 指其他未列明薯类。 | H15: 范围3 | I15: =VLOOKUP(F15,[1]完整分类结果!$E:$G,3,0) -> 农、林、牧、渔及水利业 | J15: =VLOOKUP(I15,[2]行业排放因子!$A:$B,2,0) -> 90.746323 | K15: 农业固体废弃物（Agricultural Solid Waste）
A16: 15 | B16: 农、林、牧、渔业类产品 | C16: 农业产品 | D16: 油料 | E16: 1010103010000000000 | F16: 花生 | G16: 包括带壳花生、花生仁。 | H16: 范围3 | I16: =VLOOKUP(F16,[1]完整分类结果!$E:$G,3,0) -> 农、林、牧、渔及水利业 | J16: =VLOOKUP(I16,[2]行业排放因子!$A:$B,2,0) -> 90.746323 | K16: 农业固体废弃物（Agricultural Solid Waste）
A17: 16 | B17: 农、林、牧、渔业类产品 | C17: 农业产品 | D17: 油料 | E17: 1010103020000000000 | F17: 油菜籽 | G17: 包括双低油菜籽（指低硫苷、低芥酸油菜籽）、其他油菜籽。 | H17: 范围3 | I17: =VLOOKUP(F17,[1]完整分类结果!$E:$G,3,0) -> 农、林、牧、渔及水利业 | J17: =VLOOKUP(I17,[2]行业排放因子!$A:$B,2,0) -> 90.746323 | K17: 农业固体废弃物（Agricultural Solid Waste）
A18: 17 | B18: 农、林、牧、渔业类产品 | C18: 农业产品 | D18: 油料 | E18: 1010103030000000000 | F18: 芝麻 | G18: 包括白芝麻、黑芝麻、黄芝麻。 | H18: 范围3 | I18: =VLOOKUP(F18,[1]完整分类结果!$E:$G,3,0) -> 农、林、牧、渔及水利业 | J18: =VLOOKUP(I18,[2]行业排放因子!$A:$B,2,0) -> 90.746323 | K18: 农业固体废弃物（Agricultural Solid Waste）
A19: 18 | B19: 农、林、牧、渔业类产品 | C19: 农业产品 | D19: 油料 | E19: 1010103990000000000 | F19: 其他油料 | G19: 其他含油子仁及果实，如胡麻籽、棉籽、蓖麻籽、芥子、红花籽、油棕果及油棕仁、罂粟子、油橄榄果、油茶籽（油料）等。 | H19: 范围3 | I19: =VLOOKUP(F19,[1]完整分类结果!$E:$G,3,0) -> 农、林、牧、渔及水利业 | J19: =VLOOKUP(I19,[2]行业排放因子!$A:$B,2,0) -> 90.746323 | K19: 农业固体废弃物（Agricultural Solid Waste）
A20: 19 | B20: 农、林、牧、渔业类产品 | C20: 农业产品 | D20: 干豆 | E20: 1010104010000000000 | F20: 大豆 | G20: 包括黄大豆、黑大豆、青大豆、褐红大豆、双青豆、青仁乌豆、小黑豆、其他大豆。 | H20: 范围3 | I20: =VLOOKUP(F20,[1]完整分类结果!$E:$G,3,0) -> 农、林、牧、渔及水利业 | J20: =VLOOKUP(I20,[2]行业排放因子!$A:$B,2,0) -> 90.746323 | K20: 农业固体废弃物（Agricultural Solid Waste）
A21: 20 | B21: 农、林、牧、渔业类产品 | C21: 农业产品 | D21: 干豆 | E21: 1010104020000000000 | F21: 绿豆 | G21: 包括明绿豆、毛绿豆。 | H21: 范围3 | I21: =VLOOKUP(F21,[1]完整分类结果!$E:$G,3,0) -> 农、林、牧、渔及水利业 | J21: =VLOOKUP(I21,[2]行业排放因子!$A:$B,2,0) -> 90.746323 | K21: 农业固体废弃物（Agricultural Solid Waste）
... A24: 23 | B24: 农、林、牧、渔业类产品 | C24: 农业产品 | D24: 生麻 | E24: 1010106000000000000 | F24: 生麻 | G24: 包括生亚麻、生苎麻、生黄红麻、生线麻、生苘麻、生大麻、生剑麻、其他生麻。 | H24: 范围3 | I24: =VLOOKUP(F24,[1]完整分类结果!$E:$G,3,0) -> 农、林、牧、渔及水利业 | J24: =VLOOKUP(I24,[2]行业排放因子!$A:$B,2,0) -> 90.746323 | K24: 农业固体废弃物（Agricultural Solid Waste）
A25: 24 | B25: 农、林、牧、渔业类产品 | C25: 农业产品 | D25: 糖料 | E25: 1010107010000000000 | F25: 甘蔗 | H25: 范围3 | I25: =VLOOKUP(F25,[1]完整分类结果!$E:$G,3,0) -> 农、林、牧、渔及水利业 | J25: =VLOOKUP(I25,[2]行业排放因子!$A:$B,2,0) -> 90.746323 | K25: 农业固体废弃物（Agricultural Solid Waste）
A26: 25 | B26: 农、林、牧、渔业类产品 | C26: 农业产品 | D26: 糖料 | E26: 1010107020000000000 | F26: 甜菜 | H26: 范围3 | I26: =VLOOKUP(F26,[1]完整分类结果!$E:$G,3,0) -> 农、林、牧、渔及水利业 | J26: =VLOOKUP(I26,[2]行业排放因子!$A:$B,2,0) -> 90.746323 | K26: 农业固体废弃物（Agricultural Solid Waste）
A27: 26 | B27: 农、林、牧、渔业类产品 | C27: 农业产品 | D27: 糖料 | E27: 1010107990000000000 | F27: 其他糖料 | H27: 范围3 | I27: =VLOOKUP(F27,[1]完整分类结果!$E:$G,3,0) -> 农、林、牧、渔及水利业 | J27: =VLOOKUP(I27,[2]行业排放因子!$A:$B,2,0) -> 90.746323 | K27: 农业固体废弃物（Agricultural Solid Waste）
A28: 27 | B28: 农、林、牧、渔业类产品 | C28: 农业产品 | D28: 烟草 | E28: 1010108010000000000 | F28: 未去梗烤烟叶 | G28: 指初烤未去梗烤烟叶，不包括复烤烟叶（详见1030401）。 | H28: 范围3 | I28: =VLOOKUP(F28,[1]完整分类结果!$E:$G,3,0) -> 农、林、牧、渔及水利业 | J28: =VLOOKUP(I28,[2]行业排放因子!$A:$B,2,0) -> 90.746323 | K28: 农业固体废弃物（Agricultural Solid Waste）
A29: 28 | B29: 农、林、牧、渔业类产品 | C29: 农业产品 | D29: 烟草 | E29: 1010108990000000000 | F29: 其他未加工烟草 | G29: 指其他未加工烟草，包括未去梗晒烟叶、未去梗晾烟叶、未去梗白肋烟、其他未加工烟草。 | H29: 范围3 | I29: =VLOOKUP(F29,[1]完整分类结果!$E:$G,3,0) -> 农、林、牧、渔及水利业 | J29: =VLOOKUP(I29,[2]行业排放因子!$A:$B,2,0) -> 90.746323 | K29: 农业固体废弃物（Agricultural Solid Waste）
A30: 29 | B30: 农、林、牧、渔业类产品 | C30: 农业产品 | D30: 饲料作物 | E30: 1010109010000000000 | F30: 饲料牧草 | G30: 包括苜蓿干草、羊草、沙打旺、其他饲料牧草。 | H30: 范围3 | I30: =VLOOKUP(F30,[1]完整分类结果!$E:$G,3,0) -> 农、林、牧、渔及水利业 | J30: =VLOOKUP(I30,[2]行业排放因子!$A:$B,2,0) -> 90.746323 | K30: 农业固体废弃物（Agricultural Solid Waste）
A31: 30 | B31: 农、林、牧、渔业类产品 | C31: 农业产品 | D31: 饲料作物 | E31: 1010109990000000000 | F31: 其他饲料作物 | G31: 包括青饲料、其他饲料作物。 | H31: 范围3 | I31: =VLOOKUP(F31,[1]完整分类结果!$E:$G,3,0) -> 农、林、牧、渔及水利业 | J31: =VLOOKUP(I31,[2]行业排放因子!$A:$B,2,0) -> 90.746323 | K31: 农业固体废弃物（Agricultural Solid Waste）
A32: 31 | B32: 农、林、牧、渔业类产品 | C32: 农业产品 | D32: 水生植物 | E32: 1010110000000000000 | F32: 水生植物类 | G32: 包括芦苇、席草、苇子、莲子、蒲草、慈姑、其他水生植物类。 | H32: 范围3 | I32: =VLOOKUP(F32,[1]完整分类结果!$E:$G,3,0) -> 农、林、牧、渔及水利业 | J32: =VLOOKUP(I32,[2]行业排放因子!$A:$B,2,0) -> 90.746323 | K32: 农业固体废弃物（Agricultural Solid Waste）
A33: 32 | B33: 农、林、牧、渔业类产品 | C33: 农业产品 | D33: 农副产品 | E33: 1010111010000000000 | F33: 作物茎、秆、根 | G33: 包括稻草、麦秸、谷壳、谷子秸、玉米秸、高粱秸、薯藤、大豆秸、花生蔓、油菜籽秆、芝麻秆、向日葵秆、棉花秆、麻秆、烟秆、其他作物茎、杆、根。 | H33: 范围3 | I33: =VLOOKUP(F33,[1]完整分类结果!$E:$G,3,0) -> 农、林、牧、渔及水利业 | J33: =VLOOKUP(I33,[2]行业排放因子!$A:$B,2,0) -> 90.746323 | K33: 农业固体废弃物（Agricultural Solid Waste）
A34: 33 | B34: 农、林、牧、渔业类产品 | C34: 农业产品 | D34: 农副产品 | E34: 1010111990000000000 | F34: 其他农作物副产品 | G34: 包括红黑瓜籽、园参籽等。 | H34: 范围3 | I34: =VLOOKUP(F34,[1]完整分类结果!$E:$G,3,0) -> 农、林、牧、渔及水利业 | J34: =VLOOKUP(I34,[2]行业排放因子!$A:$B,2,0) -> 90.746323 | K34: 农业固体废弃物（Agricultural Solid Waste）
A35: 34 | B35: 农、林、牧、渔业类产品 | C35: 农业产品 | D35: 蔬菜 | E35: 1010112010000000000 | F35: 萝卜等根菜类蔬菜 | G35: 包括萝卜（别名：葖、芦菔、莱菔）、胡萝卜（别名：红萝卜、黄萝卜、丁香萝卜、药性萝卜、番萝卜）、芜菁（别名：蔓菁、圆根、盘菜）、芜菁甘蓝（别名：洋蔓菁、洋疙瘩、洋大头菜）、根菾菜（别名：红菜头、紫菜头）、美洲防风（别名：欧防风芹菜萝卜、蒲芹萝卜）、牛蒡（别名：东洋萝卜、蝙蝠刺、大力子）、根芹菜（别名：根洋芹菜、球根塘蒿）、婆罗门参（别名：西洋牛蒡、蒜叶婆罗门参）、山葵）、黑婆罗门参（别名：菊牛蒡、鸦葱）。 | H35: 范围3 | I35: =VLOOKUP(F35,[1]完整分类结果!$E:$G,3,0) -> 农、林、牧、渔及水利业 | J35: =VLOOKUP(I35,[2]行业排放因子!$A:$B,2,0) -> 90.746323 | K35: 农业固体废弃物（Agricultural Solid Waste）
A36: 35 | B36: 农、林、牧、渔业类产品 | C36: 农业产品 | D36: 蔬菜 | E36: 1010112020000000000 | F36: 山药等薯芋类蔬菜 | G36: 包括姜（别名：生姜、黄姜）、芋（别名：芋头、芋艿、毛芋）、魔芋（别名：磨芋、蒟蒻）、山药（别名：薯蓣、白苕、脚板苕、山薯、大薯、佛掌薯）、豆薯（别名：地瓜、凉薯、沙葛、新罗葛）、葛、菊芋（别名：洋姜、鬼子姜）、菜用土圞儿（别名：香芋、美洲土圞儿）、蕉芋（别名：蕉藕、姜芋、食用美人蕉、食用莲蕉）、草石蚕（别名：螺丝菜、宝塔菜、甘露儿、地蚕）。不包括马铃薯（详见101010201）、甘薯（详见101010203）。 | H36: 范围3 | I36: =VLOOKUP(F36,[1]完整分类结果!$E:$G,3,0) -> 农、林、牧、渔及水利业 | J36: =VLOOKUP(I36,[2]行业排放因子!$A:$B,2,0) -> 90.746323 | K36: 农业固体废弃物（Agricultural Solid Waste）
A37: 36 | B37: 农、林、牧、渔业类产品 | C37: 农业产品 | D37: 蔬菜 | E37: 1010112030000000000 | F37: 葱蒜类蔬菜 | G37: 包括韭（别名：草钟乳、起阳草、懒人菜、韭黄）、大葱（别名：木葱、汉葱）、洋葱（别名：葱头、圆葱）、大蒜（别名：胡蒜、蒜）、蒜薹（别名：蒜苔）、蒜苗（别名：蒜黄、青蒜）、分葱（别名：四季葱、菜葱、冬葱）、胡葱（别名：蒜头葱、瓣子葱、火葱、肉葱）、细香葱（别名：四季葱、香葱、蝦夷葱）、韭葱（别名：扁葱、扁叶葱、洋蒜苗）、楼葱（别名：龙爪葱、龙角葱）、蕹（别名：藠头、藠子、莱芝）。 | H37: 范围3 | I37: =VLOOKUP(F37,[1]完整分类结果!$E:$G,3,0) -> 农、林、牧、渔及水利业 | J37: =VLOOKUP(I37,[2]行业排放因子!$A:$B,2,0) -> 90.746323 | K37: 农业固体废弃物（Agricultural Solid Waste）
A38: 37 | B38: 农、林、牧、渔业类产品 | C38: 农业产品 | D38: 蔬菜 | E38: 1010112040000000000 | F38: 白菜类蔬菜 | G38: 包括大白菜（别名：结球白菜、黄芽菜、包心白菜）、普通白菜（别名：白菜、小白菜、青菜、油菜）、乌塌菜（别名：榻菜、塌棵菜、榻地菘、黑菜）、菜薹（别名：菜心、绿菜薹、菜尖）、薹菜、紫菜薹（别名：红菜薹）。 | H38: 范围3 | I38: =VLOOKUP(F38,[1]完整分类结果!$E:$G,3,0) -> 农、林、牧、渔及水利业 | J38: =VLOOKUP(I38,[2]行业排放因子!$A:$B,2,0) -> 90.746323 | K38: 农业固体废弃物（Agricultural Solid Waste）
A39: 38 | B39: 农、林、牧、渔业类产品 | C39: 农业产品 | D39: 蔬菜 | E39: 1010112050000000000 | F39: 芥菜类蔬菜 | G39: 包括茎芥（别名：茎瘤芥、青菜头、菜头、包包菜、羊角菜、菱角菜、抱子芥、儿菜、娃娃菜、笋子芥、棒菜）、叶芥（别名：青菜、苦菜、春菜、辣菜、雪里蕻）、根芥（别名：辣疙瘩、冲菜、芥头、大头菜、疙瘩菜）、薹芥。 | H39: 范围3 | I39: =VLOOKUP(F39,[1]完整分类结果!$E:$G,3,0) -> 农、林、牧、渔及水利业 | J39: =VLOOKUP(I39,[2]行业排放因子!$A:$B,2,0) -> 90.746323 | K39: 农业固体废弃物（Agricultural Solid Waste）
... A48: 47 | B48: 农、林、牧、渔业类产品 | C48: 农业产品 | D48: 蔬菜 | E48: 1010112140000000000 | F48: 绿豆芽等芽苗菜 | G48: 包括绿豆芽（别名：绿豆芽幼芽）、黄豆芽（别名：黄豆幼芽）、黑豆芽（别名：黑豆幼芽）、青豆芽（别名：青豆幼芽）、红豆芽（别名：红豆幼芽）、蚕豆芽（别名：蚕豆幼芽）、红小豆苗（别名：红小豆幼芽）、豌豆苗（别名：豌豆幼芽）、花生芽（别名：花生幼芽）、苜蓿芽（别名：苜蓿幼芽或幼苗）、小扁豆芽（别名：小扁豆幼芽或幼苗）、萝卜芽（别名：萝卜芽幼苗）、菘蓝芽（别名：菘蓝幼芽或幼苗）、沙芥芽（别名：沙芥幼芽或幼苗）、芥菜芽（别名：芥菜幼芽或幼苗）、芥蓝芽（别名：芥蓝幼芽或幼苗）、白菜芽（别名：白菜幼芽或幼苗）、独行菜芽（别名：独行菜幼苗）、香椿苗（别名：香椿幼苗）、向日葵芽（别名：向日葵幼芽）、荞麦芽（别名：荞麦幼苗）、胡椒芽（别名：胡椒幼芽或幼苗）、紫苏芽（别名：紫苏幼芽或幼苗）、水芹芽（别名：水芹幼苗）、小麦苗（别名：小麦幼苗）、胡麻芽（别名：胡麻幼芽或幼苗）、蕹菜芽（别名：蕹菜幼苗）、芝麻芽（别名：芝麻幼芽或幼苗）、黄秋葵芽（别名：黄秋葵幼苗）、花椒脑（别名：花椒嫩芽）。 | H48: 范围3 | I48: =VLOOKUP(F48,[1]完整分类结果!$E:$G,3,0) -> 农、林、牧、渔及水利业 | J48: =VLOOKUP(I48,[2]行业排放因子!$A:$B,2,0) -> 90.746323 | K48: 农业固体废弃物（Agricultural Solid Waste）
A49: 48 | B49: 农、林、牧、渔业类产品 | C49: 农业产品 | D49: 蔬菜 | E49: 1010112150000000000 | F49: 其他蔬菜 | H49: 范围3 | I49: =VLOOKUP(F49,[1]完整分类结果!$E:$G,3,0) -> 农、林、牧、渔及水利业 | J49: =VLOOKUP(I49,[2]行业排放因子!$A:$B,2,0) -> 90.746323 | K49: 农业固体废弃物（Agricultural Solid Waste）
A50: 49 | B50: 农、林、牧、渔业类产品 | C50: 农业产品 | D50: 花卉 | E50: 1010113010000000000 | F50: 盆栽花 | G50: 包括鳞茎、块茎、块根、球茎、根颈及根茎等花卉。 | H50: 范围3 | I50: =VLOOKUP(F50,[1]完整分类结果!$E:$G,3,0) -> 农、林、牧、渔及水利业 | J50: =VLOOKUP(I50,[2]行业排放因子!$A:$B,2,0) -> 90.746323 | K50: 农业固体废弃物（Agricultural Solid Waste）
A51: 50 | B51: 农、林、牧、渔业类产品 | C51: 农业产品 | D51: 花卉 | E51: 1010113020000000000 | F51: 鲜切花及花蕾 | G51: 包括康乃馨、满天星、勿忘我、玫瑰、情人草、紫罗兰、月季、香石竹、唐菖蒲、百合花、非洲菊、补血草、马蹄莲、火鹤、其他鲜切花及花蕾。 | H51: 范围3 | I51: =VLOOKUP(F51,[1]完整分类结果!$E:$G,3,0) -> 农、林、牧、渔及水利业 | J51: =VLOOKUP(I51,[2]行业排放因子!$A:$B,2,0) -> 90.746323 | K51: 农业固体废弃物（Agricultural Solid Waste）
A52: 51 | B52: 农、林、牧、渔业类产品 | C52: 农业产品 | D52: 花卉 | E52: 1010113030000000000 | F52: 切叶 | G52: 包括肾蕨、散尾葵、苏铁、富贵竹、龟背竹、其他切叶。 | H52: 范围3 | I52: =VLOOKUP(F52,[1]完整分类结果!$E:$G,3,0) -> 农、林、牧、渔及水利业 | J52: =VLOOKUP(I52,[2]行业排放因子!$A:$B,2,0) -> 90.746323 | K52: 农业固体废弃物（Agricultural Solid Waste）
A53: 52 | B53: 农、林、牧、渔业类产品 | C53: 农业产品 | D53: 花卉 | E53: 1010113040000000000 | F53: 切枝 | G53: 包括银芽柳、其他切枝。 | H53: 范围3 | I53: =VLOOKUP(F53,[1]完整分类结果!$E:$G,3,0) -> 农、林、牧、渔及水利业 | J53: =VLOOKUP(I53,[2]行业排放因子!$A:$B,2,0) -> 90.746323 | K53: 农业固体废弃物（Agricultural Solid Waste）
A54: 53 | B54: 农、林、牧、渔业类产品 | C54: 农业产品 | D54: 花卉 | E54: 1010113050000000000 | F54: 干燥花 | G54: 指经过干制处理的花卉。 | H54: 范围3 | I54: =VLOOKUP(F54,[1]完整分类结果!$E:$G,3,0) -> 农、林、牧、渔及水利业 | J54: =VLOOKUP(I54,[2]行业排放因子!$A:$B,2,0) -> 90.746323 | K54: 农业固体废弃物（Agricultural Solid Waste）
A55: 54 | B55: 农、林、牧、渔业类产品 | C55: 农业产品 | D55: 园艺产品 | E55: 1010114010100000000 | F55: 盆栽观叶植物 | G55: 包括龙血树（巴西木）、马拉巴栗（发财树）、喜林芋、绿萝、变叶木、袖珍椰子、盆栽散尾葵、绿巨人、花叶万年青（黛粉）、竹芋、白鹤芋、花叶芋、亮丝草、其他盆栽观叶植物。 | H55: 范围3 | I55: =VLOOKUP(F55,[1]完整分类结果!$E:$G,3,0) -> 农、林、牧、渔及水利业 | J55: =VLOOKUP(I55,[2]行业排放因子!$A:$B,2,0) -> 90.746323 | K55: 农业固体废弃物（Agricultural Solid Waste）
A56: 55 | B56: 农、林、牧、渔业类产品 | C56: 农业产品 | D56: 园艺产品 | E56: 1010114010200000000 | F56: 草皮 | H56: 范围3 | I56: =VLOOKUP(F56,[1]完整分类结果!$E:$G,3,0) -> 农、林、牧、渔及水利业 | J56: =VLOOKUP(I56,[2]行业排放因子!$A:$B,2,0) -> 90.746323 | K56: 农业固体废弃物（Agricultural Solid Waste）
A57: 56 | B57: 农、林、牧、渔业类产品 | C57: 农业产品 | D57: 园艺产品 | E57: 1010114010300000000 | F57: 草坪 | H57: 范围3 | I57: =VLOOKUP(F57,[1]完整分类结果!$E:$G,3,0) -> 农、林、牧、渔及水利业 | J57: =VLOOKUP(I57,[2]行业排放因子!$A:$B,2,0) -> 90.746323 | K57: 农业固体废弃物（Agricultural Solid Waste）
A58: 57 | B58: 农、林、牧、渔业类产品 | C58: 农业产品 | D58: 园艺产品 | E58: 1010114990000000000 | F58: 其他盆景及园艺产品 | H58: 范围3 | I58: =VLOOKUP(F58,[1]完整分类结果!$E:$G,3,0) -> 农、林、牧、渔及水利业 | J58: =VLOOKUP(I58,[2]行业排放因子!$A:$B,2,0) -> 90.746323 | K58: 农业固体废弃物（Agricultural Solid Waste）
A59: 58 | B59: 农、林、牧、渔业类产品 | C59: 农业产品 | D59: 水果 | E59: 1010115010100000000 | F59: 苹果 | G59: 包括红富士苹果、国光苹果、秦冠苹果、香蕉苹果、金冠苹果、元帅苹果、新红星苹果、其他苹果。 | H59: 范围3 | I59: =VLOOKUP(F59,[1]完整分类结果!$E:$G,3,0) -> 农、林、牧、渔及水利业 | J59: =VLOOKUP(I59,[2]行业排放因子!$A:$B,2,0) -> 90.746323 | K59: 农业固体废弃物（Agricultural Solid Waste）
A60: 59 | B60: 农、林、牧、渔业类产品 | C60: 农业产品 | D60: 水果 | E60: 1010115010200000000 | F60: 梨 | G60: 包括雪花梨、鸭梨、酥梨、香梨、苹果梨、黄冠梨、绿宝石梨、冬果梨、贡梨、黄花梨、其他梨。 | H60: 范围3 | I60: =VLOOKUP(F60,[1]完整分类结果!$E:$G,3,0) -> 农、林、牧、渔及水利业 | J60: =VLOOKUP(I60,[2]行业排放因子!$A:$B,2,0) -> 90.746323 | K60: 农业固体废弃物（Agricultural Solid Waste）
A61: 60 | B61: 农、林、牧、渔业类产品 | C61: 农业产品 | D61: 水果 | E61: 1010115010300000000 | F61: 柑橘类水果 | G61: 包括柑、橘、橙、柚、柠檬等。 | H61: 范围3 | I61: =VLOOKUP(F61,[1]完整分类结果!$E:$G,3,0) -> 农、林、牧、渔及水利业 | J61: =VLOOKUP(I61,[2]行业排放因子!$A:$B,2,0) -> 90.746323 | K61: 农业固体废弃物（Agricultural Solid Waste）
A62: 61 | B62: 农、林、牧、渔业类产品 | C62: 农业产品 | D62: 水果 | E62: 1010115010400000000 | F62: 葡萄 | G62: 指鲜葡萄，包括巨峰葡萄、玫瑰香葡萄、白葡萄、龙眼葡萄、木纳格葡萄、红提葡萄、酿造葡萄、其他葡萄。 | H62: 范围3 | I62: =VLOOKUP(F62,[1]完整分类结果!$E:$G,3,0) -> 农、林、牧、渔及水利业 | J62: =VLOOKUP(I62,[2]行业排放因子!$A:$B,2,0) -> 90.746323 | K62: 农业固体废弃物（Agricultural Solid Waste）
A63: 62 | B63: 农、林、牧、渔业类产品 | C63: 农业产品 | D63: 水果 | E63: 1010115010500000000 | F63: 香蕉 | G63: 包括芭蕉。 | H63: 范围3 | I63: =VLOOKUP(F63,[1]完整分类结果!$E:$G,3,0) -> 农、林、牧、渔及水利业 | J63: =VLOOKUP(I63,[2]行业排放因子!$A:$B,2,0) -> 90.746323 | K63: 农业固体废弃物（Agricultural Solid Waste）
A64: 63 | B64: 农、林、牧、渔业类产品 | C64: 农业产品 | D64: 水果 | E64: 1010115010600000000 | F64: 菠萝 | H64: 范围3 | I64: =VLOOKUP(F64,[1]完整分类结果!$E:$G,3,0) -> 农、林、牧、渔及水利业 | J64: =VLOOKUP(I64,[2]行业排放因子!$A:$B,2,0) -> 90.746323 | K64: 农业固体废弃物（Agricultural Solid Waste）
A65: 64 | B65: 农、林、牧、渔业类产品 | C65: 农业产品 | D65: 水果 | E65: 1010115010700000000 | F65: 龙眼 | H65: 范围3 | I65: =VLOOKUP(F65,[1]完整分类结果!$E:$G,3,0) -> 农、林、牧、渔及水利业 | J65: =VLOOKUP(I65,[2]行业排放因子!$A:$B,2,0) -> 90.746323 | K65: 农业固体废弃物（Agricultural Solid Waste）
A66: 65 | B66: 农、林、牧、渔业类产品 | C66: 农业产品 | D66: 水果 | E66: 1010115010800000000 | F66: 荔枝 | H66: 范围3 | I66: =VLOOKUP(F66,[1]完整分类结果!$E:$G,3,0) -> 农、林、牧、渔及水利业 | J66: =VLOOKUP(I66,[2]行业排放因子!$A:$B,2,0) -> 90.746323 | K66: 农业固体废弃物（Agricultural Solid Waste）
A67: 66 | B67: 农、林、牧、渔业类产品 | C67: 农业产品 | D67: 水果 | E67: 1010115010900000000 | F67: 枇杷 | H67: 范围3 | I67: =VLOOKUP(F67,[1]完整分类结果!$E:$G,3,0) -> 农、林、牧、渔及水利业 | J67: =VLOOKUP(I67,[2]行业排放因子!$A:$B,2,0) -> 90.746323 | K67: 农业固体废弃物（Agricultural Solid Waste）
A68: 67 | B68: 农、林、牧、渔业类产品 | C68: 农业产品 | D68: 水果 | E68: 1010115011000000000 | F68: 红毛丹 | H68: 范围3 | I68: =VLOOKUP(F68,[1]完整分类结果!$E:$G,3,0) -> 农、林、牧、渔及水利业 | J68: =VLOOKUP(I68,[2]行业排放因子!$A:$B,2,0) -> 90.746323 | K68: 农业固体废弃物（Agricultural Solid Waste）
A69: 68 | B69: 农、林、牧、渔业类产品 | C69: 农业产品 | D69: 水果 | E69: 1010115011100000000 | F69: 芒果 | H69: 范围3 | I69: =VLOOKUP(F69,[1]完整分类结果!$E:$G,3,0) -> 农、林、牧、渔及水利业 | J69: =VLOOKUP(I69,[2]行业排放因子!$A:$B,2,0) -> 90.746323 | K69: 农业固体废弃物（Agricultural Solid Waste）
A70: 69 | B70: 农、林、牧、渔业类产品 | C70: 农业产品 | D70: 水果 | E70: 1010115011200000000 | F70: 橄榄 | H70: 范围3 | I70: =VLOOKUP(F70,[1]完整分类结果!$E:$G,3,0) -> 农、林、牧、渔及水利业 | J70: =VLOOKUP(I70,[2]行业排放因子!$A:$B,2,0) -> 90.746323 | K70: 农业固体废弃物（Agricultural Solid Waste）
A71: 70 | B71: 农、林、牧、渔业类产品 | C71: 农业产品 | D71: 水果 | E71: 1010115011300000000 | F71: 无花果 | H71: 范围3 | I71: =VLOOKUP(F71,[1]完整分类结果!$E:$G,3,0) -> 农、林、牧、渔及水利业 | J71: =VLOOKUP(I71,[2]行业排放因子!$A:$B,2,0) -> 90.746323 | K71: 农业固体废弃物（Agricultural Solid Waste）
A72: 71 | B72: 农、林、牧、渔业类产品 | C72: 农业产品 | D72: 水果 | E72: 1010115011400000000 | F72: 鳄梨 | H72: 范围3 | I72: =VLOOKUP(F72,[1]完整分类结果!$E:$G,3,0) -> 农、林、牧、渔及水利业 | J72: =VLOOKUP(I72,[2]行业排放因子!$A:$B,2,0) -> 90.746323 | K72: 农业固体废弃物（Agricultural Solid Waste）
A73: 72 | B73: 农、林、牧、渔业类产品 | C73: 农业产品 | D73: 水果 | E73: 1010115011500000000 | F73: 番石榴 | H73: 范围3 | I73: =VLOOKUP(F73,[1]完整分类结果!$E:$G,3,0) -> 农、林、牧、渔及水利业 | J73: =VLOOKUP(I73,[2]行业排放因子!$A:$B,2,0) -> 90.746323 | K73: 农业固体废弃物（Agricultural Solid Waste）
A74: 73 | B74: 农、林、牧、渔业类产品 | C74: 农业产品 | D74: 水果 | E74: 1010115011600000000 | F74: 山竹果 | H74: 范围3 | I74: =VLOOKUP(F74,[1]完整分类结果!$E:$G,3,0) -> 农、林、牧、渔及水利业 | J74: =VLOOKUP(I74,[2]行业排放因子!$A:$B,2,0) -> 90.746323 | K74: 农业固体废弃物（Agricultural Solid Waste）
A75: 74 | B75: 农、林、牧、渔业类产品 | C75: 农业产品 | D75: 水果 | E75: 1010115011700000000 | F75: 杨桃 | H75: 范围3 | I75: =VLOOKUP(F75,[1]完整分类结果!$E:$G,3,0) -> 农、林、牧、渔及水利业 | J75: =VLOOKUP(I75,[2]行业排放因子!$A:$B,2,0) -> 90.746323 | K75: 农业固体废弃物（Agricultural Solid Waste）
... A84: 83 | B84: 农、林、牧、渔业类产品 | C84: 农业产品 | D84: 水果 | E84: 1010115012600000000 | F84: 樱桃 | H84: 范围3 | I84: =VLOOKUP(F84,[1]完整分类结果!$E:$G,3,0) -> 农、林、牧、渔及水利业 | J84: =VLOOKUP(I84,[2]行业排放因子!$A:$B,2,0) -> 90.746323 | K84: 农业固体废弃物（Agricultural Solid Waste）
A85: 84 | B85: 农、林、牧、渔业类产品 | C85: 农业产品 | D85: 水果 | E85: 1010115012700000000 | F85: 枣 | G85: 指鲜枣，包括小枣、冬枣、沙枣、青枣等。 | H85: 范围3 | I85: =VLOOKUP(F85,[1]完整分类结果!$E:$G,3,0) -> 农、林、牧、渔及水利业 | J85: =VLOOKUP(I85,[2]行业排放因子!$A:$B,2,0) -> 90.746323 | K85: 农业固体废弃物（Agricultural Solid Waste）
A86: 85 | B86: 农、林、牧、渔业类产品 | C86: 农业产品 | D86: 水果 | E86: 1010115012800000000 | F86: 红果 | H86: 范围3 | I86: =VLOOKUP(F86,[1]完整分类结果!$E:$G,3,0) -> 农、林、牧、渔及水利业 | J86: =VLOOKUP(I86,[2]行业排放因子!$A:$B,2,0) -> 90.746323 | K86: 农业固体废弃物（Agricultural Solid Waste）
A87: 86 | B87: 农、林、牧、渔业类产品 | C87: 农业产品 | D87: 水果 | E87: 1010115012900000000 | F87: 柿子 | H87: 范围3 | I87: =VLOOKUP(F87,[1]完整分类结果!$E:$G,3,0) -> 农、林、牧、渔及水利业 | J87: =VLOOKUP(I87,[2]行业排放因子!$A:$B,2,0) -> 90.746323 | K87: 农业固体废弃物（Agricultural Solid Waste）
A88: 87 | B88: 农、林、牧、渔业类产品 | C88: 农业产品 | D88: 水果 | E88: 1010115013000000000 | F88: 桃 | H88: 范围3 | I88: =VLOOKUP(F88,[1]完整分类结果!$E:$G,3,0) -> 农、林、牧、渔及水利业 | J88: =VLOOKUP(I88,[2]行业排放因子!$A:$B,2,0) -> 90.746323 | K88: 农业固体废弃物（Agricultural Solid Waste）
A89: 88 | B89: 农、林、牧、渔业类产品 | C89: 农业产品 | D89: 水果 | E89: 1010115013100000000 | F89: 李子 | H89: 范围3 | I89: =VLOOKUP(F89,[1]完整分类结果!$E:$G,3,0) -> 农、林、牧、渔及水利业 | J89: =VLOOKUP(I89,[2]行业排放因子!$A:$B,2,0) -> 90.746323 | K89: 农业固体废弃物（Agricultural Solid Waste）
A90: 89 | B90: 农、林、牧、渔业类产品 | C90: 农业产品 | D90: 水果 | E90: 1010115013200000000 | F90: 石榴 | H90: 范围3 | I90: =VLOOKUP(F90,[1]完整分类结果!$E:$G,3,0) -> 农、林、牧、渔及水利业 | J90: =VLOOKUP(I90,[2]行业排放因子!$A:$B,2,0) -> 90.746323 | K90: 农业固体废弃物（Agricultural Solid Waste）
A91: 90 | B91: 农、林、牧、渔业类产品 | C91: 农业产品 | D91: 水果 | E91: 1010115013300000000 | F91: 杏 | H91: 范围3 | I91: =VLOOKUP(F91,[1]完整分类结果!$E:$G,3,0) -> 农、林、牧、渔及水利业 | J91: =VLOOKUP(I91,[2]行业排放因子!$A:$B,2,0) -> 90.746323 | K91: 农业固体废弃物（Agricultural Solid Waste）
A92: 91 | B92: 农、林、牧、渔业类产品 | C92: 农业产品 | D92: 水果 | E92: 1010115013400000000 | F92: 杨梅 | H92: 范围3 | I92: =VLOOKUP(F92,[1]完整分类结果!$E:$G,3,0) -> 农、林、牧、渔及水利业 | J92: =VLOOKUP(I92,[2]行业排放因子!$A:$B,2,0) -> 90.746323 | K92: 农业固体废弃物（Agricultural Solid Waste）
A93: 92 | B93: 农、林、牧、渔业类产品 | C93: 农业产品 | D93: 水果 | E93: 1010115013500000000 | F93: 草莓 | H93: 范围3 | I93: =VLOOKUP(F93,[1]完整分类结果!$E:$G,3,0) -> 农、林、牧、渔及水利业 | J93: =VLOOKUP(I93,[2]行业排放因子!$A:$B,2,0) -> 90.746323 | K93: 农业固体废弃物（Agricultural Solid Waste）
A94: 93 | B94: 农、林、牧、渔业类产品 | C94: 农业产品 | D94: 水果 | E94: 1010115013600000000 | F94: 黑莓 | H94: 范围3 | I94: =VLOOKUP(F94,[1]完整分类结果!$E:$G,3,0) -> 农、林、牧、渔及水利业 | J94: =VLOOKUP(I94,[2]行业排放因子!$A:$B,2,0) -> 90.746323 | K94: 农业固体废弃物（Agricultural Solid Waste）
A95: 94 | B95: 农、林、牧、渔业类产品 | C95: 农业产品 | D95: 水果 | E95: 1010115013700000000 | F95: 桑椹 | H95: 范围3 | I95: =VLOOKUP(F95,[1]完整分类结果!$E:$G,3,0) -> 农、林、牧、渔及水利业 | J95: =VLOOKUP(I95,[2]行业排放因子!$A:$B,2,0) -> 90.746323 | K95: 农业固体废弃物（Agricultural Solid Waste）
A96: 95 | B96: 农、林、牧、渔业类产品 | C96: 农业产品 | D96: 水果 | E96: 1010115013800000000 | F96: 猕猴桃 | G96: 又名奇异果 | H96: 范围3 | I96: =VLOOKUP(F96,[1]完整分类结果!$E:$G,3,0) -> 农、林、牧、渔及水利业 | J96: =VLOOKUP(I96,[2]行业排放因子!$A:$B,2,0) -> 90.746323 | K96: 农业固体废弃物（Agricultural Solid Waste）
A97: 96 | B97: 农、林、牧、渔业类产品 | C97: 农业产品 | D97: 水果 | E97: 1010115013900000000 | F97: 沙棘 | H97: 范围3 | I97: =VLOOKUP(F97,[1]完整分类结果!$E:$G,3,0) -> 农、林、牧、渔及水利业 | J97: =VLOOKUP(I97,[2]行业排放因子!$A:$B,2,0) -> 90.746323 | K97: 农业固体废弃物（Agricultural Solid Waste）
A98: 97 | B98: 农、林、牧、渔业类产品 | C98: 农业产品 | D98: 水果 | E98: 1010115019900000000 | F98: 其他未列明水果 | G98: 包括罗甘莓、木莓等。 | H98: 范围3 | I98: =VLOOKUP(F98,[1]完整分类结果!$E:$G,3,0) -> 农、林、牧、渔及水利业 | J98: =VLOOKUP(I98,[2]行业排放因子!$A:$B,2,0) -> 90.746323 | K98: 农业固体废弃物（Agricultural Solid Waste）
A99: 98 | B99: 农、林、牧、渔业类产品 | C99: 农业产品 | D99: 干制水果 | E99: 1010115020000000000 | F99: 干制水果 | G99: 包括葡萄干、杏干、梅干及李干、苹果干、龙眼干（肉）、柿饼、干枣、椰子干、荔枝干、其他干制水果。 | H99: 范围3 | I99: =VLOOKUP(F99,[1]完整分类结果!$E:$G,3,0) -> 农、林、牧、渔及水利业 | J99: =VLOOKUP(I99,[2]行业排放因子!$A:$B,2,0) -> 90.746323 | K99: 农业固体废弃物（Agricultural Solid Waste）
A100: 99 | B100: 农、林、牧、渔业类产品 | C100: 农业产品 | D100: 坚果 | E100: 1010115030100000000 | F100: 椰子 | G100: 包括种用椰子、其他椰子。 | H100: 范围3 | I100: =VLOOKUP(F100,[1]完整分类结果!$E:$G,3,0) -> 农、林、牧、渔及水利业 | J100: =VLOOKUP(I100,[2]行业排放因子!$A:$B,2,0) -> 90.746323 | K100: 农业固体废弃物（Agricultural Solid Waste）
A101: 100 | B101: 农、林、牧、渔业类产品 | C101: 农业产品 | D101: 坚果 | E101: 1010115030200000000 | F101: 腰果 | H101: 范围3 | I101: =VLOOKUP(F101,[1]完整分类结果!$E:$G,3,0) -> 农、林、牧、渔及水利业 | J101: =VLOOKUP(I101,[2]行业排放因子!$A:$B,2,0) -> 90.746323 | K101: 农业固体废弃物（Agricultural Solid Waste）
A102: 101 | B102: 农、林、牧、渔业类产品 | C102: 农业产品 | D102: 坚果 | E102: 1010115030300000000 | F102: 核桃 | H102: 范围3 | I102: =VLOOKUP(F102,[1]完整分类结果!$E:$G,3,0) -> 农、林、牧、渔及水利业 | J102: =VLOOKUP(I102,[2]行业排放因子!$A:$B,2,0) -> 90.746323 | K102: 农业固体废弃物（Agricultural Solid Waste）
A103: 102 | B103: 农、林、牧、渔业类产品 | C103: 农业产品 | D103: 坚果 | E103: 1010115030400000000 | F103: 山核桃 | H103: 范围3 | I103: =VLOOKUP(F103,[1]完整分类结果!$E:$G,3,0) -> 农、林、牧、渔及水利业 | J103: =VLOOKUP(I103,[2]行业排放因子!$A:$B,2,0) -> 90.746323 | K103: 农业固体废弃物（Agricultural Solid Waste）
A104: 103 | B104: 农、林、牧、渔业类产品 | C104: 农业产品 | D104: 坚果 | E104: 1010115030500000000 | F104: 栗子 | G104: 包括板栗、锥栗、丹东栗、其他栗子。 | H104: 范围3 | I104: =VLOOKUP(F104,[1]完整分类结果!$E:$G,3,0) -> 农、林、牧、渔及水利业 | J104: =VLOOKUP(I104,[2]行业排放因子!$A:$B,2,0) -> 90.746323 | K104: 农业固体废弃物（Agricultural Solid Waste）
A105: 104 | B105: 农、林、牧、渔业类产品 | C105: 农业产品 | D105: 坚果 | E105: 1010115030600000000 | F105: 松子 | H105: 范围3 | I105: =VLOOKUP(F105,[1]完整分类结果!$E:$G,3,0) -> 农、林、牧、渔及水利业 | J105: =VLOOKUP(I105,[2]行业排放因子!$A:$B,2,0) -> 90.746323 | K105: 农业固体废弃物（Agricultural Solid Waste）
A106: 105 | B106: 农、林、牧、渔业类产品 | C106: 农业产品 | D106: 坚果 | E106: 1010115030700000000 | F106: 榛子 | H106: 范围3 | I106: =VLOOKUP(F106,[1]完整分类结果!$E:$G,3,0) -> 农、林、牧、渔及水利业 | J106: =VLOOKUP(I106,[2]行业排放因子!$A:$B,2,0) -> 90.746323 | K106: 农业固体废弃物（Agricultural Solid Waste）
A107: 106 | B107: 农、林、牧、渔业类产品 | C107: 农业产品 | D107: 坚果 | E107: 1010115030800000000 | F107: 阿月浑子果（开心果） | H107: 范围3 | I107: =VLOOKUP(F107,[1]完整分类结果!$E:$G,3,0) -> 农、林、牧、渔及水利业 | J107: =VLOOKUP(I107,[2]行业排放因子!$A:$B,2,0) -> 90.746323 | K107: 农业固体废弃物（Agricultural Solid Waste）
A108: 107 | B108: 农、林、牧、渔业类产品 | C108: 农业产品 | D108: 坚果 | E108: 1010115030900000000 | F108: 槟榔 | H108: 范围3 | I108: =VLOOKUP(F108,[1]完整分类结果!$E:$G,3,0) -> 农、林、牧、渔及水利业 | J108: =VLOOKUP(I108,[2]行业排放因子!$A:$B,2,0) -> 90.746323 | K108: 农业固体废弃物（Agricultural Solid Waste）
A109: 108 | B109: 农、林、牧、渔业类产品 | C109: 农业产品 | D109: 坚果 | E109: 1010115031000000000 | F109: 白果 | H109: 范围3 | I109: =VLOOKUP(F109,[1]完整分类结果!$E:$G,3,0) -> 农、林、牧、渔及水利业 | J109: =VLOOKUP(I109,[2]行业排放因子!$A:$B,2,0) -> 90.746323 | K109: 农业固体废弃物（Agricultural Solid Waste）
A110: 109 | B110: 农、林、牧、渔业类产品 | C110: 农业产品 | D110: 坚果 | E110: 1010115031100000000 | F110: 香榧 | H110: 范围3 | I110: =VLOOKUP(F110,[1]完整分类结果!$E:$G,3,0) -> 农、林、牧、渔及水利业 | J110: =VLOOKUP(I110,[2]行业排放因子!$A:$B,2,0) -> 90.746323 | K110: 农业固体废弃物（Agricultural Solid Waste）
A111: 110 | B111: 农、林、牧、渔业类产品 | C111: 农业产品 | D111: 坚果 | E111: 1010115031200000000 | F111: 巴旦杏 | H111: 范围3 | I111: =VLOOKUP(F111,[1]完整分类结果!$E:$G,3,0) -> 农、林、牧、渔及水利业 | J111: =VLOOKUP(I111,[2]行业排放因子!$A:$B,2,0) -> 90.746323 | K111: 农业固体废弃物（Agricultural Solid Waste）
A112: 111 | B112: 农、林、牧、渔业类产品 | C112: 农业产品 | D112: 坚果 | E112: 1010115031300000000 | F112: 夏威夷果 | G112: 又名“澳洲坚果”、山龙眼科、澳洲坚果属、生长在热带地区 | H112: 范围3 | I112: =VLOOKUP(F112,[1]完整分类结果!$E:$G,3,0) -> 农、林、牧、渔及水利业 | J112: =VLOOKUP(I112,[2]行业排放因子!$A:$B,2,0) -> 90.746323 | K112: 农业固体废弃物（Agricultural Solid Waste）
A113: 112 | B113: 农、林、牧、渔业类产品 | C113: 农业产品 | D113: 坚果 | E113: 1010115039900000000 | F113: 其他食用坚果 | H113: 范围3 | I113: =VLOOKUP(F113,[1]完整分类结果!$E:$G,3,0) -> 农、林、牧、渔及水利业 | J113: =VLOOKUP(I113,[2]行业排放因子!$A:$B,2,0) -> 90.746323 | K113: 农业固体废弃物（Agricultural Solid Waste）
A114: 113 | B114: 农、林、牧、渔业类产品 | C114: 农业产品 | D114: 茶及饮料 | E114: 1010116010000000000 | F114: 茶叶 | G114: 指茶农采集和经过初加工（如炒制、晾晒）的毛茶。如红毛茶、绿毛茶、乌龙毛茶、白毛茶、黑毛茶等。 | H114: 范围3 | I114: =VLOOKUP(F114,[1]完整分类结果!$E:$G,3,0) -> 农、林、牧、渔及水利业 | J114: =VLOOKUP(I114,[2]行业排放因子!$A:$B,2,0) -> 90.746323 | K114: 农业固体废弃物（Agricultural Solid Waste）
A115: 114 | B115: 农、林、牧、渔业类产品 | C115: 农业产品 | D115: 茶及饮料 | E115: 1010116020000000000 | F115: 饮料原料 | G115: 包括可可豆、咖啡豆。 | H115: 范围3 | I115: =VLOOKUP(F115,[1]完整分类结果!$E:$G,3,0) -> 农、林、牧、渔及水利业 | J115: =VLOOKUP(I115,[2]行业排放因子!$A:$B,2,0) -> 90.746323 | K115: 农业固体废弃物（Agricultural Solid Waste）
A116: 115 | B116: 农、林、牧、渔业类产品 | C116: 农业产品 | D116: 茶及饮料 | E116: 1010116990000000000 | F116: 其他未列明饮料原料 | H116: 范围3 | I116: =VLOOKUP(F116,[1]完整分类结果!$E:$G,3,0) -> 农、林、牧、渔及水利业 | J116: =VLOOKUP(I116,[2]行业排放因子!$A:$B,2,0) -> 90.746323 | K116: 农业固体废弃物（Agricultural Solid Waste）
A117: 116 | B117: 农、林、牧、渔业类产品 | C117: 农业产品 | D117: 香料原料 | E117: 1010117000000000000 | F117: 香料原料 | G117: 指未研磨香料原料，包括调味香料（如花椒、胡椒、八椒、桂皮、桂花、丁香、豆蔻、小茴香、咖喱、枯茗子、蒿子、杜松果等）、香味料（香子兰、香茅草、留兰香、番红花、姜黄、啤酒花、麝香草、月桂叶等）。不包括研磨过香料原料（详见103020604）。 | H117: 范围3 | I117: =VLOOKUP(F117,[1]完整分类结果!$E:$G,3,0) -> 农、林、牧、渔及水利业 | J117: =VLOOKUP(I117,[2]行业排放因子!$A:$B,2,0) -> 90.746323 | K117: 农业固体废弃物（Agricultural Solid Waste）
A118: 117 | B118: 农、林、牧、渔业类产品 | C118: 农业产品 | D118: 中草药材 | E118: 1010118000000000000 | F118: 中草药材 | G118: 指主要作香料、药料、杀虫、杀菌等用途的植物。包括甘草、人参、古柯叶、罂粟杆、当归、田七、党参、黄连、菊花、冬虫夏草、贝母、川芎、半夏、白芍、天麻、黄芪、大黄、籽黄、白术、地黄、槐米、杜仲、茯苓、枸杞、大海子、沉香、沙参、青蒿、鱼藤根、除虫菊、灵芝、五味子、刺五加、生地、麦冬、云木香、白芷、元胡、山茱萸、莲翘、辛荑、厚朴、黄芩、葛根、柴胡、麻黄、列当、肉苁蓉、锁阳、罗布麻等。 | H118: 范围3 | I118: =VLOOKUP(F118,[1]完整分类结果!$E:$G,3,0) -> 农、林、牧、渔及水利业 | J118: =VLOOKUP(I118,[2]行业排放因子!$A:$B,2,0) -> 90.746323 | K118: 农业固体废弃物（Agricultural Solid Waste）
...

Sheet 服务发票税收分类编码
A1: 序号 | B1: 一级分类 | C1: 二级分类 | D1: 商品和服务分类简称 | E1: 税收分类编码 | F1: 货物和劳务名称 | G1: 说明 | H1: 碳排放范围分类 | I1: 所属行业 | J1: 对应行业排放因子
A2: 1 | B2: 劳务 | C2: 加工劳务 | D2: 劳务 | E2: 2010200000000000000 | F2: 垃圾处理、污泥处理处置劳务 | G2: 垃圾处理是指运用填埋、焚烧、综合处理和回收利用等形式，对垃圾进行减量化、资源化和无害化处理处置的业务。污泥处理处置是指对污水处理后产生的污泥进行稳定化、减量化和无害化处理处置的业务。 | H2: 范围3 | I2: =VLOOKUP(F2,[3]分类结果!$F:$G,2,0) -> 废品废料 | J2: =VLOOKUP(I2,[2]行业排放因子!$A:$B,2,0) -> 7.1376023
A3: 2 | B3: 劳务 | C3: 加工劳务 | D3: 劳务 | E3: 2010300000000000000 | F3: 污水处理劳务 | G3: 指将污水（包括城镇污水和工业废水）处理后达到《城镇污水处理厂污染物排放标准》（GB18918-2002），或达到相应的国家或地方水污染物排放标准中的直接排放限值的业务。其中，城镇污水是指城镇居民生活污水，机关、学校、医院、商业服务机构及各种公共设施排水，以及允许排入城镇污水收集系统的工业废水和初期雨水。工业废水是指工业生产过程中产生的，不允许排入城镇污水收集系统的废水和废液。 | H3: 范围3 | I3: =VLOOKUP(F3,[3]分类结果!$F:$G,2,0) -> 其他制造业 | J3: =VLOOKUP(I3,[2]行业排放因子!$A:$B,2,0) -> 0.24541556
A4: 3 | B4: 劳务 | C4: 加工劳务 | D4: 劳务 | E4: 2010400000000000000 | F4: 工业废气处理劳务 | G4: 指专门针对工业场所如工厂、车间产生的废气在对外排放前进行预处理，以达到国家废气对外排放标准的工作。 | H4: 范围3 | I4: =VLOOKUP(F4,[3]分类结果!$F:$G,2,0) -> 其他制造业 | J4: =VLOOKUP(I4,[2]行业排放因子!$A:$B,2,0) -> 0.24541556
A5: 4 | B5: 劳务 | C5: 加工劳务 | D5: 劳务 | E5: 2010500000000000000 | F5: 其他加工劳务 | G5: 指除稀土冶炼分离产品加工劳务、垃圾处理、污泥处理处置劳务、污水处理劳务、工业废气处理劳务以外的其他加工劳务。 | H5: 范围3 | I5: =VLOOKUP(F5,[3]分类结果!$F:$G,2,0) -> 其他制造业 | J5: =VLOOKUP(I5,[2]行业排放因子!$A:$B,2,0) -> 0.24541556
A6: 5 | B6: 劳务 | C6: 修理修配劳务 | D6: 劳务 | E6: 2020000000000000000 | F6: 修理修配劳务 | G6: 指受托对损伤和丧失功能的货物进行修复，使其恢复原状和功能的业务。 | H6: 范围3 | I6: =VLOOKUP(F6,[3]分类结果!$F:$G,2,0) -> 其他制造业 | J6: =VLOOKUP(I6,[2]行业排放因子!$A:$B,2,0) -> 0.24541556
A7: 6 | B7: 劳务 | C7: 其他劳务 | D7: 劳务 | E7: 2030000000000000000 | F7: 油气田企业为生产原油、天然气提供的生产性劳务 | G7: 生产性劳务是指油气田企业为生产原油、天然气，从地质普查、勘探开发到原油天然气销售的一系列生产过程所发生的劳务（具体见《增值税生产性劳务征税范围注释》）。 | H7: 范围3 | I7: =VLOOKUP(F7,[3]分类结果!$F:$G,2,0) -> 石油和天然气开采业 | J7: =VLOOKUP(I7,[2]行业排放因子!$A:$B,2,0) -> 44.014305
A8: 7 | B8: 劳务 | C8: 其他劳务 | D8: 劳务 | E8: 2040000000000000000 | F8: 矿产资源开采、挖掘、切割、破碎、分拣、洗选等劳务 | G8: 包括矿产资源开采、挖掘、切割、破碎、分拣、洗选等。 | H8: 范围3 | I8: =VLOOKUP(F8,[3]分类结果!$F:$G,2,0) -> 其他制造业 | J8: =VLOOKUP(I8,[2]行业排放因子!$A:$B,2,0) -> 0.24541556
A9: 8 | B9: 销售服务 | C9: 交通运输服务 | D9: 运输服务 | E9: 3010101010100000000 | F9: 国内铁路旅客运输服务 | G9: 指起运地和目的地都在境内的铁路旅客运输业务活动。 | H9: 范围3 | I9: =VLOOKUP(F9,[3]分类结果!$F:$G,2,0) -> 交通运输、仓储、邮电通信业 | J9: =VLOOKUP(I9,[2]行业排放因子!$A:$B,2,0) -> 667.48066
A10: 9 | B10: 销售服务 | C10: 交通运输服务 | D10: 运输服务 | E10: 3010101010200000000 | F10: 国际铁路旅客运输服务 | G10: 指通过铁路从境内载运旅客出境、从境外载运旅客入境，以及在境外载运旅客的运输业务活动。 | H10: 范围3 | I10: =VLOOKUP(F10,[3]分类结果!$F:$G,2,0) -> 交通运输、仓储、邮电通信业 | J10: =VLOOKUP(I10,[2]行业排放因子!$A:$B,2,0) -> 667.48066
A11: 10 | B11: 销售服务 | C11: 交通运输服务 | D11: 运输服务 | E11: 3010101010300000000 | F11: 港澳台铁路旅客运输服务 | G11: 指通过铁路往返香港、澳门、台湾，以及在香港、澳门、台湾提供的旅客运输业务活动。 | H11: 范围3 | I11: =VLOOKUP(F11,[3]分类结果!$F:$G,2,0) -> 交通运输、仓储、邮电通信业 | J11: =VLOOKUP(I11,[2]行业排放因子!$A:$B,2,0) -> 667.48066
A12: 11 | B12: 销售服务 | C12: 交通运输服务 | D12: 运输服务 | E12: 3010101020101010000 | F12: 国内长途汽车旅客运输服务 | G12: 指起运地和目的地都在境内的长途旅客运输业务活动，含长途班车服务。 | H12: 范围3 | I12: =VLOOKUP(F12,[3]分类结果!$F:$G,2,0) -> 交通运输设备制造业 | J12: =VLOOKUP(I12,[2]行业排放因子!$A:$B,2,0) -> 6.2441374
A13: 12 | B13: 销售服务 | C13: 交通运输服务 | D13: 运输服务 | E13: 3010101020101020000 | F13: 国际长途汽车旅客运输服务 | G13: 指通过道路从境内载运旅客出境、从境外载运旅客入境，以及在境外载运旅客的运输业务活动。 | H13: 范围3 | I13: =VLOOKUP(F13,[3]分类结果!$F:$G,2,0) -> 交通运输设备制造业 | J13: =VLOOKUP(I13,[2]行业排放因子!$A:$B,2,0) -> 6.2441374
... A18: 17 | B18: 销售服务 | C18: 交通运输服务 | D18: 运输服务 | E18: 3010101020203000000 | F18: 出租汽车客运服务 | G18: 指轿车出租计程、轿车出租包车、中型客车出租、大型客车出租客运业务活动，含城市班车服务。 | H18: 范围3 | I18: =VLOOKUP(F18,[3]分类结果!$F:$G,2,0) -> 交通运输设备制造业 | J18: =VLOOKUP(I18,[2]行业排放因子!$A:$B,2,0) -> 6.2441374
A19: 18 | B19: 销售服务 | C19: 交通运输服务 | D19: 运输服务 | E19: 3010101020204000000 | F19: 索道客运服务 | H19: 范围3 | I19: =VLOOKUP(F19,[3]分类结果!$F:$G,2,0) -> 其他制造业 | J19: =VLOOKUP(I19,[2]行业排放因子!$A:$B,2,0) -> 0.24541556
A20: 19 | B20: 销售服务 | C20: 交通运输服务 | D20: 运输服务 | E20: 3010101020299000000 | F20: 其他城市旅客公共交通服务 | G20: 指其他未列明的城市旅客运输活动。 | H20: 范围3 | I20: =VLOOKUP(F20,[3]分类结果!$F:$G,2,0) -> 交通运输、仓储、邮电通信业 | J20: =VLOOKUP(I20,[2]行业排放因子!$A:$B,2,0) -> 667.48066
A21: 20 | B21: 销售服务 | C21: 交通运输服务 | D21: 运输服务 | E21: 3010102010100000000 | F21: 国内铁路货物运输服务 | G21: 指起运地、目的地都在境内的铁路货物运输业务活动。 | H21: 范围3 | I21: =VLOOKUP(F21,[3]分类结果!$F:$G,2,0) -> 交通运输、仓储、邮电通信业 | J21: =VLOOKUP(I21,[2]行业排放因子!$A:$B,2,0) -> 667.48066
A22: 21 | B22: 销售服务 | C22: 交通运输服务 | D22: 运输服务 | E22: 3010102010200000000 | F22: 国际铁路货物运输服务 | G22: 指通过铁路从境内载运货物出境、从境外载运货物入境以及在境外载运货物的运输业务活动。 | H22: 范围3 | I22: =VLOOKUP(F22,[3]分类结果!$F:$G,2,0) -> 交通运输、仓储、邮电通信业 | J22: =VLOOKUP(I22,[2]行业排放因子!$A:$B,2,0) -> 667.48066
A23: 22 | B23: 销售服务 | C23: 交通运输服务 | D23: 运输服务 | E23: 3010102010300000000 | F23: 港澳台铁路货物运输服务 | G23: 指通过铁路往返香港、澳门、台湾以及在香港、澳门、台湾提供的货物运输业务活动。 | H23: 范围3 | I23: =VLOOKUP(F23,[3]分类结果!$F:$G,2,0) -> 交通运输、仓储、邮电通信业 | J23: =VLOOKUP(I23,[2]行业排放因子!$A:$B,2,0) -> 667.48066
A24: 23 | B24: 销售服务 | C24: 交通运输服务 | D24: 运输服务 | E24: 3010102020100000000 | F24: 国内道路货物运输服务 | G24: 指起运地、目的地都在境内的道路货物运输业务活动。 | H24: 范围3 | I24: =VLOOKUP(F24,[3]分类结果!$F:$G,2,0) -> 交通运输、仓储、邮电通信业 | J24: =VLOOKUP(I24,[2]行业排放因子!$A:$B,2,0) -> 667.48066
A25: 24 | B25: 销售服务 | C25: 交通运输服务 | D25: 运输服务 | E25: 3010102020200000000 | F25: 国际道路货物运输服务 | G25: 指通过道路从境内载运货物出境、从境外载运货物入境以及在境外载运货物的运输业务活动。 | H25: 范围3 | I25: =VLOOKUP(F25,[3]分类结果!$F:$G,2,0) -> 交通运输、仓储、邮电通信业 | J25: =VLOOKUP(I25,[2]行业排放因子!$A:$B,2,0) -> 667.48066
A26: 25 | B26: 销售服务 | C26: 交通运输服务 | D26: 运输服务 | E26: 3010102020300000000 | F26: 港澳台道路货物运输服务 | G26: 指通过道路往返香港、澳门、台湾以及在香港、澳门、台湾提供的货物运输业务活动。 | H26: 范围3 | I26: =VLOOKUP(F26,[3]分类结果!$F:$G,2,0) -> 交通运输、仓储、邮电通信业 | J26: =VLOOKUP(I26,[2]行业排放因子!$A:$B,2,0) -> 667.48066
A27: 26 | B27: 销售服务 | C27: 交通运输服务 | D27: 运输服务 | E27: 3010102990100000000 | F27: 国内其他陆路货物运输服务 | G27: 指起运地、目的地都在境内的其他陆路货物运输业务。 | H27: 范围3 | I27: =VLOOKUP(F27,[3]分类结果!$F:$G,2,0) -> 交通运输、仓储、邮电通信业 | J27: =VLOOKUP(I27,[2]行业排放因子!$A:$B,2,0) -> 667.48066
A28: 27 | B28: 销售服务 | C28: 交通运输服务 | D28: 运输服务 | E28: 3010102990200000000 | F28: 国际其他陆路货物运输服务 | G28: 指通过其他陆运方式从境内载运货物出境、从境外载运货物入境以及在境外载运货物的运输业务活动。 | H28: 范围3 | I28: =VLOOKUP(F28,[3]分类结果!$F:$G,2,0) -> 交通运输、仓储、邮电通信业 | J28: =VLOOKUP(I28,[2]行业排放因子!$A:$B,2,0) -> 667.48066
A29: 28 | B29: 销售服务 | C29: 交通运输服务 | D29: 运输服务 | E29: 3010102990300000000 | F29: 港澳台其他陆路货物运输服务 | G29: 指通过其他陆运方式往返香港、澳门、台湾以及在香港、澳门、台湾提供的货物运输业务活动。 | H29: 范围3 | I29: =VLOOKUP(F29,[3]分类结果!$F:$G,2,0) -> 交通运输、仓储、邮电通信业 | J29: =VLOOKUP(I29,[2]行业排放因子!$A:$B,2,0) -> 667.48066
A30: 29 | B30: 销售服务 | C30: 交通运输服务 | D30: 运输服务 | E30: 3010201010000000000 | F30: 国内水路旅客运输服务 | G30: 指起运地和目的地都在境内的水路旅客运输业务活动，含轮客渡服务。 | H30: 范围3 | I30: =VLOOKUP(F30,[3]分类结果!$F:$G,2,0) -> 交通运输、仓储、邮电通信业 | J30: =VLOOKUP(I30,[2]行业排放因子!$A:$B,2,0) -> 667.48066
A31: 30 | B31: 销售服务 | C31: 交通运输服务 | D31: 运输服务 | E31: 3010201020000000000 | F31: 国际水路旅客运输服务 | G31: 指通过水路运输方式在境内载运旅客出境、从境外载运旅客入境以及在境外载运旅客的运输业务活动。 | H31: 范围3 | I31: =VLOOKUP(F31,[3]分类结果!$F:$G,2,0) -> 交通运输、仓储、邮电通信业 | J31: =VLOOKUP(I31,[2]行业排放因子!$A:$B,2,0) -> 667.48066
... A70: 69 | B70: 销售服务 | C70: 交通运输服务 | D70: 运输服务 | E70: 3010506020000000000 | F70: 无运输工具承运货物联运运输服务 | G70: 指经营者以承运人身份与托运人签订货物联运运输服务合同，收取运费并承担承运人责任，然后委托实际承运人利用多种运输工具完成运输服务的经营活动。 | H70: 范围3 | I70: =VLOOKUP(F70,[3]分类结果!$F:$G,2,0) -> 交通运输、仓储、邮电通信业 | J70: =VLOOKUP(I70,[2]行业排放因子!$A:$B,2,0) -> 667.48066
A71: 70 | B71: 销售服务 | C71: 交通运输服务 | D71: 运输服务 | E71: 3010599010000000000 | F71: 其他无运输工具承运旅客运输业务 | H71: 范围3 | I71: =VLOOKUP(F71,[3]分类结果!$F:$G,2,0) -> 交通运输、仓储、邮电通信业 | J71: =VLOOKUP(I71,[2]行业排放因子!$A:$B,2,0) -> 667.48066
A72: 71 | B72: 销售服务 | C72: 交通运输服务 | D72: 运输服务 | E72: 3010599020000000000 | F72: 其他无运输工具承运货物运输业务 | H72: 范围3 | I72: =VLOOKUP(F72,[3]分类结果!$F:$G,2,0) -> 交通运输、仓储、邮电通信业 | J72: =VLOOKUP(I72,[2]行业排放因子!$A:$B,2,0) -> 667.48066
A73: 72 | B73: 销售服务 | C73: 交通运输服务 | D73: 运输服务 | E73: 3010601000000000000 | F73: 旅客联运服务 | G73: 指利用多种运输工具载运旅客的业务活动。 | H73: 范围3 | I73: =VLOOKUP(F73,[3]分类结果!$F:$G,2,0) -> 交通运输、仓储、邮电通信业 | J73: =VLOOKUP(I73,[2]行业排放因子!$A:$B,2,0) -> 667.48066
A74: 73 | B74: 销售服务 | C74: 交通运输服务 | D74: 运输服务 | E74: 3010602000000000000 | F74: 货物联运服务 | G74: 指利用多种运输工具载运货物的业务活动。 | H74: 范围3 | I74: =VLOOKUP(F74,[3]分类结果!$F:$G,2,0) -> 交通运输、仓储、邮电通信业 | J74: =VLOOKUP(I74,[2]行业排放因子!$A:$B,2,0) -> 667.48066
A75: 74 | B75: 销售服务 | C75: 交通运输服务 | D75: 运输服务 | E75: 3019901000000000000 | F75: 其他旅客运输服务 | H75: 范围3 | I75: =VLOOKUP(F75,[3]分类结果!$F:$G,2,0) -> 交通运输、仓储、邮电通信业 | J75: =VLOOKUP(I75,[2]行业排放因子!$A:$B,2,0) -> 667.48066
A76: 75 | B76: 销售服务 | C76: 交通运输服务 | D76: 运输服务 | E76: 3019902000000000000 | F76: 其他货物运输服务 | H76: 范围3 | I76: =VLOOKUP(F76,[3]分类结果!$F:$G,2,0) -> 交通运输、仓储、邮电通信业 | J76: =VLOOKUP(I76,[2]行业排放因子!$A:$B,2,0) -> 667.48066
A77: 76 | B77: 销售服务 | C77: 邮政服务 | D77: 邮政服务 | E77: 3020101010000000000 | F77: 函件寄递服务 | G77: 指信函、印刷品、邮资封片卡、无名址函件和邮政小包等的寄递服务业务。 | H77: 范围3 | I77: =VLOOKUP(F77,[3]分类结果!$F:$G,2,0) -> 印刷业、记录媒介复制业 | J77: =VLOOKUP(I77,[2]行业排放因子!$A:$B,2,0) -> 1.44956
A78: 77 | B78: 销售服务 | C78: 邮政服务 | D78: 邮政服务 | E78: 3020101020000000000 | F78: 包裹寄递服务 | G78: 指寄递包裹的业务，包裹是指按照封装上的名址递送给特定个人或者单位的独立封装的物品，其重量不超过五十千克，任何一边的尺寸不超过一百五十厘米，长、宽、高合计不超过三百厘米。 | H78: 范围3 | I78: =VLOOKUP(F78,[3]分类结果!$F:$G,2,0) -> 其他制造业 | J78: =VLOOKUP(I78,[2]行业排放因子!$A:$B,2,0) -> 0.24541556
A79: 78 | B79: 销售服务 | C79: 邮政服务 | D79: 邮政服务 | E79: 3020101990000000000 | F79: 其他邮件寄递服务 | G79: 指除函件、包裹以外的邮件寄递服务。 | H79: 范围3 | I79: =VLOOKUP(F79,[3]分类结果!$F:$G,2,0) -> 其他制造业 | J79: =VLOOKUP(I79,[2]行业排放因子!$A:$B,2,0) -> 0.24541556
A80: 79 | B80: 销售服务 | C80: 邮政服务 | D80: 邮政服务 | E80: 3020102000000000000 | F80: 邮票发行服务 | H80: 范围3 | I80: =VLOOKUP(F80,[3]分类结果!$F:$G,2,0) -> 其他制造业 | J80: =VLOOKUP(I80,[2]行业排放因子!$A:$B,2,0) -> 0.24541556
A81: 80 | B81: 销售服务 | C81: 邮政服务 | D81: 邮政服务 | E81: 3020103000000000000 | F81: 报刊发行服务 | H81: 范围3 | I81: =VLOOKUP(F81,[3]分类结果!$F:$G,2,0) -> 其他制造业 | J81: =VLOOKUP(I81,[2]行业排放因子!$A:$B,2,0) -> 0.24541556
A82: 81 | B82: 销售服务 | C82: 邮政服务 | D82: 邮政服务 | E82: 3020104000000000000 | F82: 邮政汇兑 | H82: 范围3 | I82: =VLOOKUP(F82,[3]分类结果!$F:$G,2,0) -> 交通运输、仓储、邮电通信业 | J82: =VLOOKUP(I82,[2]行业排放因子!$A:$B,2,0) -> 667.48066
A83: 82 | B83: 销售服务 | C83: 邮政服务 | D83: 邮政服务 | E83: 3020199000000000000 | F83: 其他邮政普遍服务 | H83: 范围3 | I83: =VLOOKUP(F83,[3]分类结果!$F:$G,2,0) -> 交通运输、仓储、邮电通信业 | J83: =VLOOKUP(I83,[2]行业排放因子!$A:$B,2,0) -> 667.48066
A84: 83 | B84: 销售服务 | C84: 邮政服务 | D84: 邮政服务 | E84: 3020200000000000000 | F84: 邮政特殊服务 | G84: 指义务兵平常信函、机要通信、盲人读物和革命烈士遗物的寄递等业务活动。 | H84: 范围3 | I84: =VLOOKUP(F84,[3]分类结果!$F:$G,2,0) -> 交通运输、仓储、邮电通信业 | J84: =VLOOKUP(I84,[2]行业排放因子!$A:$B,2,0) -> 667.48066
A85: 84 | B85: 销售服务 | C85: 邮政服务 | D85: 邮政服务 | E85: 3020301000000000000 | F85: 邮册等邮品销售服务 | H85: 范围3 | I85: =VLOOKUP(F85,[3]分类结果!$F:$G,2,0) -> 批发、零售和餐饮业 | J85: =VLOOKUP(I85,[2]行业排放因子!$A:$B,2,0) -> 55.43039
A86: 85 | B86: 销售服务 | C86: 邮政服务 | D86: 邮政服务 | E86: 3020302000000000000 | F86: 邮政代理服务 | H86: 范围3 | I86: =VLOOKUP(F86,[3]分类结果!$F:$G,2,0) -> 交通运输、仓储、邮电通信业 | J86: =VLOOKUP(I86,[2]行业排放因子!$A:$B,2,0) -> 667.48066
A87: 86 | B87: 销售服务 | C87: 邮政服务 | D87: 邮政服务 | E87: 3020399000000000000 | F87: 其他未列邮政服务 | H87: 范围3 | I87: =VLOOKUP(F87,[3]分类结果!$F:$G,2,0) -> 交通运输、仓储、邮电通信业 | J87: =VLOOKUP(I87,[2]行业排放因子!$A:$B,2,0) -> 667.48066
A88: 87 | B88: 销售服务 | C88: 电信服务 | D88: 电信服务 | E88: 3030101000000000000 | F88: 语音通话服务 | H88: 范围3 | I88: =VLOOKUP(F88,[3]分类结果!$F:$G,2,0) -> 其他制造业 | J88: =VLOOKUP(I88,[2]行业排放因子!$A:$B,2,0) -> 0.24541556
A89: 88 | B89: 销售服务 | C89: 电信服务 | D89: 电信服务 | E89: 3030102000000000000 | F89: 出租或出售网络元素 | H89: 范围3 | I89: =VLOOKUP(F89,[3]分类结果!$F:$G,2,0) -> 其他制造业 | J89: =VLOOKUP(I89,[2]行业排放因子!$A:$B,2,0) -> 0.24541556
A90: 89 | B90: 销售服务 | C90: 电信服务 | D90: 电信服务 | E90: 3030201000000000000 | F90: 短信和彩信服务 | H90: 范围3 | I90: =VLOOKUP(F90,[3]分类结果!$F:$G,2,0) -> 其他制造业 | J90: =VLOOKUP(I90,[2]行业排放因子!$A:$B,2,0) -> 0.24541556
A91: 90 | B91: 销售服务 | C91: 电信服务 | D91: 电信服务 | E91: 3030202000000000000 | F91: 电子数据和信息的传输及应用服务 | H91: 范围3 | I91: =VLOOKUP(F91,[3]分类结果!$F:$G,2,0) -> 电子及通信设备制造业 | J91: =VLOOKUP(I91,[2]行业排放因子!$A:$B,2,0) -> 7.5202869
A92: 91 | B92: 销售服务 | C92: 电信服务 | D92: 电信服务 | E92: 3030203000000000000 | F92: 互联网接入服务 | H92: 范围3 | I92: =VLOOKUP(F92,[3]分类结果!$F:$G,2,0) -> 其他制造业 | J92: =VLOOKUP(I92,[2]行业排放因子!$A:$B,2,0) -> 0.24541556
A93: 92 | B93: 销售服务 | C93: 电信服务 | D93: 电信服务 | E93: 3030204000000000000 | F93: 广播电视信号传输服务 | H93: 范围3 | I93: =VLOOKUP(F93,[3]分类结果!$F:$G,2,0) -> 其他制造业 | J93: =VLOOKUP(I93,[2]行业排放因子!$A:$B,2,0) -> 0.24541556
A94: 93 | B94: 销售服务 | C94: 电信服务 | D94: 电信服务 | E94: 3030205000000000000 | F94: 卫星电视信号落地转接服务 | H94: 范围3 | I94: =VLOOKUP(F94,[3]分类结果!$F:$G,2,0) -> 其他制造业 | J94: =VLOOKUP(I94,[2]行业排放因子!$A:$B,2,0) -> 0.24541556
A95: 94 | B95: 销售服务 | C95: 电信服务 | D95: 电信服务 | E95: 3030299000000000000 | F95: 其他增值电信服务 | G95: 指除短信和彩信服务、电子数据和信息的传输及应用服务、互联网接入服务、广播电视信号传输服务以外的增值电信服务。 | H95: 范围3 | I95: =VLOOKUP(F95,[3]分类结果!$F:$G,2,0) -> 电子及通信设备制造业 | J95: =VLOOKUP(I95,[2]行业排放因子!$A:$B,2,0) -> 7.5202869
A96: 95 | B96: 销售服务 | C96: 现代服务 | D96: 研发和技术服务 | E96: 3040101000000000000 | F96: 研发服务 | G96: 指就新技术、新产品、新工艺或者新材料及其系统进行研究与试验开发的业务活动。 | H96: 范围3 | I96: =VLOOKUP(F96,[3]分类结果!$F:$G,2,0) -> 其他制造业 | J96: =VLOOKUP(I96,[2]行业排放因子!$A:$B,2,0) -> 0.24541556
A97: 96 | B97: 销售服务 | C97: 现代服务 | D97: 研发和技术服务 | E97: 3040103000000000000 | F97: 合同能源管理服务 | G97: 指节能服务公司与用能单位以契约形式约定节能目标，节能服务公司提供必要的服务，用能单位以节能效果支付节能服务公司投入及其合理报酬的业务活动。 | H97: 范围3 | I97: =VLOOKUP(F97,[3]分类结果!$F:$G,2,0) -> 其他制造业 | J97: =VLOOKUP(I97,[2]行业排放因子!$A:$B,2,0) -> 0.24541556
A98: 97 | B98: 销售服务 | C98: 现代服务 | D98: 研发和技术服务 | E98: 3040104010000000000 | F98: 工程勘察服务 | G98: 指研究和查明工程建设场地的地质地理环境特征的服务。 | H98: 范围3 | I98: =VLOOKUP(F98,[3]分类结果!$F:$G,2,0) -> 建筑业 | J98: =VLOOKUP(I98,[2]行业排放因子!$A:$B,2,0) -> 41.715972
A99: 98 | B99: 销售服务 | C99: 现代服务 | D99: 研发和技术服务 | E99: 3040104020100000000 | F99: 矿产地质勘查服务 | G99: 指运用找矿方法、手段系统收集勘查区地质矿产信息资料，了解或查明勘查区地质特征、含矿特征、矿石质量、资源量、采选冶条件等。 | H99: 范围3 | I99: =VLOOKUP(F99,[3]分类结果!$F:$G,2,0) -> 其他制造业 | J99: =VLOOKUP(I99,[2]行业排放因子!$A:$B,2,0) -> 0.24541556
A100: 99 | B100: 销售服务 | C100: 现代服务 | D100: 研发和技术服务 | E100: 3040104020200000000 | F100: 基础地质勘查服务 | G100: 指区域、海洋、环境和水文地质勘查活动。 | H100: 范围3 | I100: =VLOOKUP(F100,[3]分类结果!$F:$G,2,0) -> 其他制造业 | J100: =VLOOKUP(I100,[2]行业排放因子!$A:$B,2,0) -> 0.24541556
A101: 100 | B101: 销售服务 | C101: 现代服务 | D101: 研发和技术服务 | E101: 3040104029900000000 | F101: 其他地质勘查服务 | H101: 范围3 | I101: =VLOOKUP(F101,[3]分类结果!$F:$G,2,0) -> 其他制造业 | J101: =VLOOKUP(I101,[2]行业排放因子!$A:$B,2,0) -> 0.24541556
A102: 101 | B102: 销售服务 | C102: 现代服务 | D102: 研发和技术服务 | E102: 3040105000000000000 | F102: 专业技术服务 | G102: 指气象服务、地震服务、海洋服务、测绘服务、城市规划、环境与生态监测服务等专项技术服务。 | H102: 范围3 | I102: =VLOOKUP(F102,[3]分类结果!$F:$G,2,0) -> 其他制造业 | J102: =VLOOKUP(I102,[2]行业排放因子!$A:$B,2,0) -> 0.24541556
A103: 102 | B103: 销售服务 | C103: 现代服务 | D103: 信息技术服务 | E103: 3040201010000000000 | F103: 软件开发服务 | G103: 包括对基础软件、应用软件、嵌入式软件等软件提供的开发服务。 | H103: 范围3 | I103: =VLOOKUP(F103,[3]分类结果!$F:$G,2,0) -> 其他制造业 | J103: =VLOOKUP(I103,[2]行业排放因子!$A:$B,2,0) -> 0.24541556
A104: 103 | B104: 销售服务 | C104: 现代服务 | D104: 信息技术服务 | E104: 3040201030000000000 | F104: 软件维护服务 | G104: 包括对基础软件、应用软件、嵌入式软件等软件提供的维护服务。 | H104: 范围3 | I104: =VLOOKUP(F104,[3]分类结果!$F:$G,2,0) -> 其他制造业 | J104: =VLOOKUP(I104,[2]行业排放因子!$A:$B,2,0) -> 0.24541556
A105: 104 | B105: 销售服务 | C105: 现代服务 | D105: 信息技术服务 | E105: 3040201050000000000 | F105: 税控技术维护服务 | G105: 服务单位为使用金税盘、税控盘等税控专用设备的纳税人提供的增值税税控系统技术维护服务，不包括增值服务。 | H105: 范围3 | I105: =VLOOKUP(F105,[3]分类结果!$F:$G,2,0) -> 专用设备制造业 | J105: =VLOOKUP(I105,[2]行业排放因子!$A:$B,2,0) -> 2.3522392
A106: 105 | B106: 销售服务 | C106: 现代服务 | D106: 信息技术服务 | E106: 3040201040000000000 | F106: 软件测试服务 | G106: 包括对基础软件、应用软件、嵌入式软件等软件提供的测试服务。 | H106: 范围3 | I106: =VLOOKUP(F106,[3]分类结果!$F:$G,2,0) -> 其他制造业 | J106: =VLOOKUP(I106,[2]行业排放因子!$A:$B,2,0) -> 0.24541556
A107: 106 | B107: 销售服务 | C107: 现代服务 | D107: 信息技术服务 | E107: 3040201990000000000 | F107: 其他软件服务 | G107: 指除软件开发、软件咨询、软件维护、软件测试以外的其他软件服务。 | H107: 范围3 | I107: =VLOOKUP(F107,[3]分类结果!$F:$G,2,0) -> 其他制造业 | J107: =VLOOKUP(I107,[2]行业排放因子!$A:$B,2,0) -> 0.24541556
A108: 107 | B108: 销售服务 | C108: 现代服务 | D108: 信息技术服务 | E108: 3040202010000000000 | F108: 电路设计服务 | G108: 指对集成电路、电子电路产品等提供的设计服务。 | H108: 范围3 | I108: =VLOOKUP(F108,[3]分类结果!$F:$G,2,0) -> 电子及通信设备制造业 | J108: =VLOOKUP(I108,[2]行业排放因子!$A:$B,2,0) -> 7.5202869
A109: 108 | B109: 销售服务 | C109: 现代服务 | D109: 信息技术服务 | E109: 3040202020000000000 | F109: 电路测试服务 | G109: 指对集成电路、电子电路产品等提供的测试服务。 | H109: 范围3 | I109: =VLOOKUP(F109,[3]分类结果!$F:$G,2,0) -> 电子及通信设备制造业 | J109: =VLOOKUP(I109,[2]行业排放因子!$A:$B,2,0) -> 7.5202869
A110: 109 | B110: 销售服务 | C110: 现代服务 | D110: 信息技术服务 | E110: 3040202030000000000 | F110: 相关电路技术支持服务 | G110: 指对集成电路、电子电路产品等提供的技术支持服务。 | H110: 范围3 | I110: =VLOOKUP(F110,[3]分类结果!$F:$G,2,0) -> 电子及通信设备制造业 | J110: =VLOOKUP(I110,[2]行业排放因子!$A:$B,2,0) -> 7.5202869
A111: 110 | B111: 销售服务 | C111: 现代服务 | D111: 信息技术服务 | E111: 3040203000000000000 | F111: 信息系统服务 | G111: 是指提供信息系统集成、网络管理、网站内容维护、桌面管理与维护、信息系统应用、基础信息技术管理平台整合、信息技术基础设施管理、数据中心、托管中心、信息安全服务、在线杀毒、虚拟主机等业务活动。包括网站对非自有的网络游戏提供的网络运营服务。 | H111: 范围3 | I111: =VLOOKUP(F111,[3]分类结果!$F:$G,2,0) -> 其他制造业 | J111: =VLOOKUP(I111,[2]行业排放因子!$A:$B,2,0) -> 0.24541556
A112: 111 | B112: 销售服务 | C112: 现代服务 | D112: 信息技术服务 | E112: 3040204000000000000 | F112: 业务流程管理服务 | G112: 是指依托信息技术提供的人力资源管理、财务经济管理、审计管理、税务管理、物流信息管理、经营信息管理和呼叫中心等服务的活动。 | H112: 范围3 | I112: =VLOOKUP(F112,[3]分类结果!$F:$G,2,0) -> 交通运输、仓储、邮电通信业 | J112: =VLOOKUP(I112,[2]行业排放因子!$A:$B,2,0) -> 667.48066
A113: 112 | B113: 销售服务 | C113: 现代服务 | D113: 信息技术服务 | E113: 3040205000000000000 | F113: 信息系统增值服务 | G113: 指利用信息系统资源为用户附加提供的信息技术服务。包括数据处理、分析和整合、数据库管理、数据备份、数据存储、容灾服务、电子商务平台等。 | H113: 范围3 | I113: =VLOOKUP(F113,[3]分类结果!$F:$G,2,0) -> 电子及通信设备制造业 | J113: =VLOOKUP(I113,[2]行业排放因子!$A:$B,2,0) -> 7.5202869
... A115: 114 | B115: 销售服务 | C115: 现代服务 | D115: 设计服务 | E115: 3040301020000000000 | F115: 专业设计服务 | G115: 包括工业设计、造型设计、服装设计、环境设计、平面设计、包装设计、动漫设计、网游设计、展示设计、网站设计、机械设计、广告设计等。2016年5月1日起停用，归入304010403 | H115: 范围3 | I115: =VLOOKUP(F115,[3]分类结果!$F:$G,2,0) -> 服装及其他纤维制品制造业 | J115: =VLOOKUP(I115,[2]行业排放因子!$A:$B,2,0) -> 0.7225285
A116: 115 | B116: 销售服务 | C116: 现代服务 | D116: 设计服务 | E116: 3040301030000000000 | F116: 文印晒图服务 | H116: 范围3 | I116: =VLOOKUP(F116,[3]分类结果!$F:$G,2,0) -> 其他制造业 | J116: =VLOOKUP(I116,[2]行业排放因子!$A:$B,2,0) -> 0.24541556
A117: 116 | B117: 销售服务 | C117: 现代服务 | D117: 设计服务 | E117: 3040301990000000000 | F117: 其他设计服务 | G117: 包括创意策划等其他设计服务。 | H117: 范围3 | I117: =VLOOKUP(F117,[3]分类结果!$F:$G,2,0) -> 其他制造业 | J117: =VLOOKUP(I117,[2]行业排放因子!$A:$B,2,0) -> 0.24541556
A118: 117 | B118: 销售服务 | C118: 现代服务 | D118: 设计服务 | E118: 3040302000000000000 | F118: 知识产权服务 | G118: 指处理知识产权事务的业务活动。包括对专利、商标、著作权、软件、集成电路布图设计的登记、鉴定、评估、认证、检索服务。 | H118: 范围3 | I118: =VLOOKUP(F118,[3]分类结果!$F:$G,2,0) -> 电子及通信设备制造业 | J118: =VLOOKUP(I118,[2]行业排放因子!$A:$B,2,0) -> 7.5202869
A119: 118 | B119: 销售服务 | C119: 现代服务 | D119: 广告服务 | E119: 3040303010100000000 | F119: 影视、广播广告发布服务 | G119: 指利用广播、电视、电影等形式进行的广告发布服务。 | H119: 范围3 | I119: =VLOOKUP(F119,[3]分类结果!$F:$G,2,0) -> 其他制造业 | J119: =VLOOKUP(I119,[2]行业排放因子!$A:$B,2,0) -> 0.24541556
A120: 119 | B120: 销售服务 | C120: 现代服务 | D120: 广告服务 | E120: 3040303010200000000 | F120: 报纸、杂志广告发布服务 | G120: 指利用图书、报纸、杂志等形式进行的广告发布服务。 | H120: 范围3 | I120: =VLOOKUP(F120,[3]分类结果!$F:$G,2,0) -> 其他制造业 | J120: =VLOOKUP(I120,[2]行业排放因子!$A:$B,2,0) -> 0.24541556
A121: 120 | B121: 销售服务 | C121: 现代服务 | D121: 广告服务 | E121: 3040303010300000000 | F121: 灯箱广告发布服务 | G121: 指利用灯箱等形式进行的广告发布服务。 | H121: 范围3 | I121: =VLOOKUP(F121,[3]分类结果!$F:$G,2,0) -> 其他制造业 | J121: =VLOOKUP(I121,[2]行业排放因子!$A:$B,2,0) -> 0.24541556
A122: 121 | B122: 销售服务 | C122: 现代服务 | D122: 广告服务 | E122: 3040303010400000000 | F122: 路牌广告发布服务 | G122: 指利用路牌等形式进行的广告发布服务。 | H122: 范围3 | I122: =VLOOKUP(F122,[3]分类结果!$F:$G,2,0) -> 其他制造业 | J122: =VLOOKUP(I122,[2]行业排放因子!$A:$B,2,0) -> 0.24541556
A123: 122 | B123: 销售服务 | C123: 现代服务 | D123: 广告服务 | E123: 3040303010500000000 | F123: 建筑物广告发布服务 | G123: 指利用外墙等建筑物结构进行的广告发布服务。 | H123: 范围3 | I123: =VLOOKUP(F123,[3]分类结果!$F:$G,2,0) -> 建筑业 | J123: =VLOOKUP(I123,[2]行业排放因子!$A:$B,2,0) -> 41.715972
A124: 123 | B124: 销售服务 | C124: 现代服务 | D124: 广告服务 | E124: 3040303010600000000 | F124: 互联网广告发布服务 | G124: 指利用互联网等形式进行的广告发布服务。 | H124: 范围3 | I124: =VLOOKUP(F124,[3]分类结果!$F:$G,2,0) -> 其他制造业 | J124: =VLOOKUP(I124,[2]行业排放因子!$A:$B,2,0) -> 0.24541556
A125: 124 | B125: 销售服务 | C125: 现代服务 | D125: 广告服务 | E125: 3040303010700000000 | F125: 流动广告发布服务 | G125: 指利用机动车、非机动车车体等进行的广告发布服务，以及受雇人员身穿广告服装等进行的广告发布服务。 | H125: 范围3 | I125: =VLOOKUP(F125,[3]分类结果!$F:$G,2,0) -> 服装及其他纤维制品制造业 | J125: =VLOOKUP(I125,[2]行业排放因子!$A:$B,2,0) -> 0.7225285
A126: 125 | B126: 销售服务 | C126: 现代服务 | D126: 广告服务 | E126: 3040303019900000000 | F126: 其他广告发布服务 | H126: 范围3 | I126: =VLOOKUP(F126,[3]分类结果!$F:$G,2,0) -> 其他制造业 | J126: =VLOOKUP(I126,[2]行业排放因子!$A:$B,2,0) -> 0.24541556
A127: 126 | B127: 销售服务 | C127: 现代服务 | D127: 广告代理服务 | E127: 3040303020000000000 | F127: 广告代理服务 | G127: 指广告经营者接受广告主或广告发布者委托，从事广告媒介安排等经营活动。 | H127: 范围3 | I127: =VLOOKUP(F127,[3]分类结果!$F:$G,2,0) -> 其他制造业 | J127: =VLOOKUP(I127,[2]行业排放因子!$A:$B,2,0) -> 0.24541556
A128: 127 | B128: 销售服务 | C128: 现代服务 | D128: 会展服务 | E128: 3040304010000000000 | F128: 会议服务 | G128: 包括国际会议服务、国内会议服务及会议中心服务。 | H128: 范围3 | I128: =VLOOKUP(F128,[3]分类结果!$F:$G,2,0) -> 其他制造业 | J128: =VLOOKUP(I128,[2]行业排放因子!$A:$B,2,0) -> 0.24541556
A129: 128 | B129: 销售服务 | C129: 现代服务 | D129: 会展服务 | E129: 3040304020000000000 | F129: 展览服务 | G129: 包括为博览会、专业技术产品展览、生活消费品展览、文化产品展览、进出口交易展会、一般产品展会、产品订货展会等提供的展览服务。 | H129: 范围3 | I129: =VLOOKUP(F129,[3]分类结果!$F:$G,2,0) -> 其他制造业 | J129: =VLOOKUP(I129,[2]行业排放因子!$A:$B,2,0) -> 0.24541556
A130: 129 | B130: 销售服务 | C130: 现代服务 | D130: 物流辅助服务 | E130: 3040401010100000000 | F130: 机场服务 | H130: 范围3 | I130: =VLOOKUP(F130,[3]分类结果!$F:$G,2,0) -> 其他制造业 | J130: =VLOOKUP(I130,[2]行业排放因子!$A:$B,2,0) -> 0.24541556
A131: 130 | B131: 销售服务 | C131: 现代服务 | D131: 物流辅助服务 | E131: 3040401010200000000 | F131: 空中交通管理服务 | H131: 范围3 | I131: =VLOOKUP(F131,[3]分类结果!$F:$G,2,0) -> 其他制造业 | J131: =VLOOKUP(I131,[2]行业排放因子!$A:$B,2,0) -> 0.24541556
A132: 131 | B132: 销售服务 | C132: 现代服务 | D132: 物流辅助服务 | E132: 3040401019900000000 | F132: 其他航空地面服务 | H132: 范围3 | I132: =VLOOKUP(F132,[3]分类结果!$F:$G,2,0) -> 交通运输、仓储、邮电通信业 | J132: =VLOOKUP(I132,[2]行业排放因子!$A:$B,2,0) -> 667.48066
A133: 132 | B133: 销售服务 | C133: 现代服务 | D133: 物流辅助服务 | E133: 3040401020100000000 | F133: 航空摄影 | H133: 范围3 | I133: =VLOOKUP(F133,[3]分类结果!$F:$G,2,0) -> 交通运输、仓储、邮电通信业 | J133: =VLOOKUP(I133,[2]行业排放因子!$A:$B,2,0) -> 667.48066
A134: 133 | B134: 销售服务 | C134: 现代服务 | D134: 物流辅助服务 | E134: 3040401020200000000 | F134: 航空培训 | H134: 范围3 | I134: =VLOOKUP(F134,[3]分类结果!$F:$G,2,0) -> 交通运输、仓储、邮电通信业 | J134: =VLOOKUP(I134,[2]行业排放因子!$A:$B,2,0) -> 667.48066
A135: 134 | B135: 销售服务 | C135: 现代服务 | D135: 物流辅助服务 | E135: 3040401020300000000 | F135: 航空测量 | H135: 范围3 | I135: =VLOOKUP(F135,[3]分类结果!$F:$G,2,0) -> 交通运输、仓储、邮电通信业 | J135: =VLOOKUP(I135,[2]行业排放因子!$A:$B,2,0) -> 667.48066
A136: 135 | B136: 销售服务 | C136: 现代服务 | D136: 物流辅助服务 | E136: 3040401020400000000 | F136: 航空勘探 | H136: 范围3 | I136: =VLOOKUP(F136,[3]分类结果!$F:$G,2,0) -> 交通运输、仓储、邮电通信业 | J136: =VLOOKUP(I136,[2]行业排放因子!$A:$B,2,0) -> 667.48066
A137: 136 | B137: 销售服务 | C137: 现代服务 | D137: 物流辅助服务 | E137: 3040401020500000000 | F137: 航空护林 | H137: 范围3 | I137: =VLOOKUP(F137,[3]分类结果!$F:$G,2,0) -> 交通运输、仓储、邮电通信业 | J137: =VLOOKUP(I137,[2]行业排放因子!$A:$B,2,0) -> 667.48066
A138: 137 | B138: 销售服务 | C138: 现代服务 | D138: 物流辅助服务 | E138: 3040401020600000000 | F138: 航空播洒农药 | H138: 范围3 | I138: =VLOOKUP(F138,[3]分类结果!$F:$G,2,0) -> 农、林、牧、渔及水利业 | J138: =VLOOKUP(I138,[2]行业排放因子!$A:$B,2,0) -> 90.746323
A139: 138 | B139: 销售服务 | C139: 现代服务 | D139: 物流辅助服务 | E139: 3040401020700000000 | F139: 航空降雨 | H139: 范围3 | I139: =VLOOKUP(F139,[3]分类结果!$F:$G,2,0) -> 交通运输、仓储、邮电通信业 | J139: =VLOOKUP(I139,[2]行业排放因子!$A:$B,2,0) -> 667.48066
A140: 139 | B140: 销售服务 | C140: 现代服务 | D140: 物流辅助服务 | E140: 3040401029900000000 | F140: 其他通用航空服务 | H140: 范围3 | I140: =VLOOKUP(F140,[3]分类结果!$F:$G,2,0) -> 交通运输、仓储、邮电通信业 | J140: =VLOOKUP(I140,[2]行业排放因子!$A:$B,2,0) -> 667.48066
A141: 140 | B141: 销售服务 | C141: 现代服务 | D141: 物流辅助服务 | E141: 3040402010000000000 | F141: 客运港口码头服务 | H141: 范围3 | I141: =VLOOKUP(F141,[3]分类结果!$F:$G,2,0) -> 其他制造业 | J141: =VLOOKUP(I141,[2]行业排放因子!$A:$B,2,0) -> 0.24541556
... A145: 144 | B145: 销售服务 | C145: 现代服务 | D145: 物流辅助服务 | E145: 3040403020000000000 | F145: 道路货运客运场站服务 | H145: 范围3 | I145: =VLOOKUP(F145,[3]分类结果!$F:$G,2,0) -> 其他制造业 | J145: =VLOOKUP(I145,[2]行业排放因子!$A:$B,2,0) -> 0.24541556
A146: 145 | B146: 销售服务 | C146: 现代服务 | D146: 物流辅助服务 | E146: 3040404000000000000 | F146: 打捞救助服务 | G146: 指提供船舶人员救助、船舶财产救助、水上救助和沉船沉物打捞服务的业务活动。 | H146: 范围3 | I146: =VLOOKUP(F146,[3]分类结果!$F:$G,2,0) -> 交通运输设备制造业 | J146: =VLOOKUP(I146,[2]行业排放因子!$A:$B,2,0) -> 6.2441374
...
